{
    "jobs": [
        {
            "job_id": 0,
            "operations": [
                {
                    "job_id": 0,
                    "op_id": 0,
                    "machine": 2,
                    "processing_time": 10.629153835354632,
                    "setup_time": 0.0,
                    "status": "pending"
                },
                {
                    "job_id": 0,
                    "op_id": 1,
                    "machine": 4,
                    "processing_time": 7.687875209147442,
                    "setup_time": 1.9773871496602338,
                    "status": "pending"
                },
                {
                    "job_id": 0,
                    "op_id": 2,
                    "machine": 1,
                    "processing_time": 10.990776962489743,
                    "setup_time": 0.008730045074969661,
                    "status": "pending"
                },
                {
                    "job_id": 0,
                    "op_id": 3,
                    "machine": 1,
                    "processing_time": 14.31227041455733,
                    "setup_time": 2.3430953359031976,
                    "status": "pending"
                }
            ],
            "arrival_time": 14,
            "completed_operations": 0,
            "priority": 3,
            "machine_seq": [
                2,
                4,
                1,
                1
            ],
            "current_operation": 0
        },
        {
            "job_id": 1,
            "operations": [
                {
                    "job_id": 1,
                    "op_id": 0,
                    "machine": 6,
                    "processing_time": 3.2926684056084916,
                    "setup_time": 0.0,
                    "status": "pending"
                },
                {
                    "job_id": 1,
                    "op_id": 1,
                    "machine": 8,
                    "processing_time": 11.600915371877557,
                    "setup_time": 1.445020048012602,
                    "status": "pending"
                },
                {
                    "job_id": 1,
                    "op_id": 2,
                    "machine": 8,
                    "processing_time": 14.051709750111783,
                    "setup_time": 1.9689000217613382,
                    "status": "pending"
                },
                {
                    "job_id": 1,
                    "op_id": 3,
                    "machine": 7,
                    "processing_time": 11.21875119429142,
                    "setup_time": 0.5276760286870559,
                    "status": "pending"
                },
                {
                    "job_id": 1,
                    "op_id": 4,
                    "machine": 5,
                    "processing_time": 5.421889909371888,
                    "setup_time": 1.376164580143989,
                    "status": "pending"
                },
                {
                    "job_id": 1,
                    "op_id": 5,
                    "machine": 6,
                    "processing_time": 13.90716079659076,
                    "setup_time": 0.15261565466374216,
                    "status": "pending"
                },
                {
                    "job_id": 1,
                    "op_id": 6,
                    "machine": 5,
                    "processing_time": 14.746655221126652,
                    "setup_time": 2.000944445416737,
                    "status": "pending"
                }
            ],
            "arrival_time": 19,
            "completed_operations": 0,
            "priority": 1,
            "machine_seq": [
                6,
                8,
                8,
                7,
                5,
                6,
                5
            ],
            "current_operation": 0
        },
        {
            "job_id": 2,
            "operations": [
                {
                    "job_id": 2,
                    "op_id": 0,
                    "machine": 8,
                    "processing_time": 10.423904637525373,
                    "setup_time": 0.0,
                    "status": "pending"
                },
                {
                    "job_id": 2,
                    "op_id": 1,
                    "machine": 3,
                    "processing_time": 10.179149703833195,
                    "setup_time": 0.31521800991730575,
                    "status": "pending"
                },
                {
                    "job_id": 2,
                    "op_id": 2,
                    "machine": 6,
                    "processing_time": 15.32393773378168,
                    "setup_time": 1.837105673878602,
                    "status": "pending"
                }
            ],
            "arrival_time": 34,
            "completed_operations": 0,
            "priority": 5,
            "machine_seq": [
                8,
                3,
                6
            ],
            "current_operation": 0
        },
        {
            "job_id": 3,
            "operations": [
                {
                    "job_id": 3,
                    "op_id": 0,
                    "machine": 0,
                    "processing_time": 2.510045913183264,
                    "setup_time": 0.0,
                    "status": "pending"
                },
                {
                    "job_id": 3,
                    "op_id": 1,
                    "machine": 7,
                    "processing_time": 11.41649935452986,
                    "setup_time": 0.5317748164444491,
                    "status": "pending"
                },
                {
                    "job_id": 3,
                    "op_id": 2,
                    "machine": 4,
                    "processing_time": 12.568333388063557,
                    "setup_time": 2.326048110732712,
                    "status": "pending"
                }
            ],
            "arrival_time": 40,
            "completed_operations": 0,
            "priority": 2,
            "machine_seq": [
                0,
                7,
                4
            ],
            "current_operation": 0
        },
        {
            "job_id": 4,
            "operations": [
                {
                    "job_id": 4,
                    "op_id": 0,
                    "machine": 9,
                    "processing_time": 5.523421602923936,
                    "setup_time": 0.0,
                    "status": "pending"
                },
                {
                    "job_id": 4,
                    "op_id": 1,
                    "machine": 5,
                    "processing_time": 8.224730068263904,
                    "setup_time": 1.4052152855584548,
                    "status": "pending"
                },
                {
                    "job_id": 4,
                    "op_id": 2,
                    "machine": 1,
                    "processing_time": 12.093078570233397,
                    "setup_time": 0.8187122989052014,
                    "status": "pending"
                }
            ],
            "arrival_time": 35,
            "completed_operations": 0,
            "priority": 4,
            "machine_seq": [
                9,
                5,
                1
            ],
            "current_operation": 0
        },
        {
            "job_id": 5,
            "operations": [
                {
                    "job_id": 5,
                    "op_id": 0,
                    "machine": 0,
                    "processing_time": 18.267623925763814,
                    "setup_time": 0.0,
                    "status": "pending"
                },
                {
                    "job_id": 5,
                    "op_id": 1,
                    "machine": 4,
                    "processing_time": 10.71795187694655,
                    "setup_time": 1.9356696568547902,
                    "status": "pending"
                },
                {
                    "job_id": 5,
                    "op_id": 2,
                    "machine": 4,
                    "processing_time": 7.291955324311649,
                    "setup_time": 0.22724781303177943,
                    "status": "pending"
                },
                {
                    "job_id": 5,
                    "op_id": 3,
                    "machine": 8,
                    "processing_time": 10.949431701363117,
                    "setup_time": 2.0383043439484565,
                    "status": "pending"
                },
                {
                    "job_id": 5,
                    "op_id": 4,
                    "machine": 0,
                    "processing_time": 11.233606463574963,
                    "setup_time": 2.324856699965847,
                    "status": "pending"
                },
                {
                    "job_id": 5,
                    "op_id": 5,
                    "machine": 5,
                    "processing_time": 12.456122371282698,
                    "setup_time": 0.38445786391600434,
                    "status": "pending"
                },
                {
                    "job_id": 5,
                    "op_id": 6,
                    "machine": 1,
                    "processing_time": 14.348268622712743,
                    "setup_time": 0.40462798053192617,
                    "status": "pending"
                }
            ],
            "arrival_time": 38,
            "completed_operations": 0,
            "priority": 3,
            "machine_seq": [
                0,
                4,
                4,
                8,
                0,
                5,
                1
            ],
            "current_operation": 0
        },
        {
            "job_id": 6,
            "operations": [
                {
                    "job_id": 6,
                    "op_id": 0,
                    "machine": 4,
                    "processing_time": 12.82778539527985,
                    "setup_time": 0.0,
                    "status": "pending"
                },
                {
                    "job_id": 6,
                    "op_id": 1,
                    "machine": 4,
                    "processing_time": 11.928135942382614,
                    "setup_time": 1.953961507837232,
                    "status": "pending"
                },
                {
                    "job_id": 6,
                    "op_id": 2,
                    "machine": 1,
                    "processing_time": 18.721616660360688,
                    "setup_time": 2.2270982456839437,
                    "status": "pending"
                },
                {
                    "job_id": 6,
                    "op_id": 3,
                    "machine": 0,
                    "processing_time": 7.836423075222532,
                    "setup_time": 1.7832468774966332,
                    "status": "pending"
                }
            ],
            "arrival_time": 35,
            "completed_operations": 0,
            "priority": 5,
            "machine_seq": [
                4,
                4,
                1,
                0
            ],
            "current_operation": 0
        },
        {
            "job_id": 7,
            "operations": [
                {
                    "job_id": 7,
                    "op_id": 0,
                    "machine": 7,
                    "processing_time": 10.02646080874057,
                    "setup_time": 0.0,
                    "status": "pending"
                },
                {
                    "job_id": 7,
                    "op_id": 1,
                    "machine": 4,
                    "processing_time": 10.339310607229105,
                    "setup_time": 1.1549204117638199,
                    "status": "pending"
                },
                {
                    "job_id": 7,
                    "op_id": 2,
                    "machine": 4,
                    "processing_time": 10.140201379396327,
                    "setup_time": 2.6165172941784856,
                    "status": "pending"
                },
                {
                    "job_id": 7,
                    "op_id": 3,
                    "machine": 7,
                    "processing_time": 16.55658570683439,
                    "setup_time": 0.68302818661765,
                    "status": "pending"
                },
                {
                    "job_id": 7,
                    "op_id": 4,
                    "machine": 6,
                    "processing_time": 12.972260891249627,
                    "setup_time": 1.0132062513491884,
                    "status": "pending"
                }
            ],
            "arrival_time": 36,
            "completed_operations": 0,
            "priority": 2,
            "machine_seq": [
                7,
                4,
                4,
                7,
                6
            ],
            "current_operation": 0
        },
        {
            "job_id": 8,
            "operations": [
                {
                    "job_id": 8,
                    "op_id": 0,
                    "machine": 1,
                    "processing_time": 8.682899406949423,
                    "setup_time": 0.0,
                    "status": "pending"
                },
                {
                    "job_id": 8,
                    "op_id": 1,
                    "machine": 9,
                    "processing_time": 10.964683013066193,
                    "setup_time": 0.202434219076974,
                    "status": "pending"
                },
                {
                    "job_id": 8,
                    "op_id": 2,
                    "machine": 8,
                    "processing_time": 11.803032840009442,
                    "setup_time": 1.870106285727539,
                    "status": "pending"
                },
                {
                    "job_id": 8,
                    "op_id": 3,
                    "machine": 3,
                    "processing_time": 7.515773918081369,
                    "setup_time": 1.4114315274989888,
                    "status": "pending"
                },
                {
                    "job_id": 8,
                    "op_id": 4,
                    "machine": 8,
                    "processing_time": 16.69813950303222,
                    "setup_time": 1.1492248721853002,
                    "status": "pending"
                },
                {
                    "job_id": 8,
                    "op_id": 5,
                    "machine": 8,
                    "processing_time": 9.936451032386561,
                    "setup_time": 1.2126931472667382,
                    "status": "pending"
                }
            ],
            "arrival_time": 9,
            "completed_operations": 0,
            "priority": 4,
            "machine_seq": [
                1,
                9,
                8,
                3,
                8,
                8
            ],
            "current_operation": 0
        },
        {
            "job_id": 9,
            "operations": [
                {
                    "job_id": 9,
                    "op_id": 0,
                    "machine": 1,
                    "processing_time": 8.350064035661855,
                    "setup_time": 0.0,
                    "status": "pending"
                },
                {
                    "job_id": 9,
                    "op_id": 1,
                    "machine": 6,
                    "processing_time": 10.310153791699724,
                    "setup_time": 2.298773420851876,
                    "status": "pending"
                },
                {
                    "job_id": 9,
                    "op_id": 2,
                    "machine": 2,
                    "processing_time": 14.622206394519374,
                    "setup_time": 0.8622267471100704,
                    "status": "pending"
                },
                {
                    "job_id": 9,
                    "op_id": 3,
                    "machine": 1,
                    "processing_time": 11.028238497573252,
                    "setup_time": 2.6702562451887286,
                    "status": "pending"
                },
                {
                    "job_id": 9,
                    "op_id": 4,
                    "machine": 1,
                    "processing_time": 14.186510573561304,
                    "setup_time": 2.198574267271256,
                    "status": "pending"
                }
            ],
            "arrival_time": 17,
            "completed_operations": 0,
            "priority": 3,
            "machine_seq": [
                1,
                6,
                2,
                1,
                1
            ],
            "current_operation": 0
        },
        {
            "job_id": 10,
            "operations": [
                {
                    "job_id": 10,
                    "op_id": 0,
                    "machine": 0,
                    "processing_time": 16.18335574203108,
                    "setup_time": 0.0,
                    "status": "pending"
                },
                {
                    "job_id": 10,
                    "op_id": 1,
                    "machine": 3,
                    "processing_time": 16.759216883418848,
                    "setup_time": 0.21725572246655833,
                    "status": "pending"
                },
                {
                    "job_id": 10,
                    "op_id": 2,
                    "machine": 4,
                    "processing_time": 10.637056349821687,
                    "setup_time": 2.175355478377756,
                    "status": "pending"
                },
                {
                    "job_id": 10,
                    "op_id": 3,
                    "machine": 6,
                    "processing_time": 15.452567403980089,
                    "setup_time": 0.9337142112703999,
                    "status": "pending"
                },
                {
                    "job_id": 10,
                    "op_id": 4,
                    "machine": 5,
                    "processing_time": 13.23908209553704,
                    "setup_time": 0.5643957206959277,
                    "status": "pending"
                }
            ],
            "arrival_time": 18,
            "completed_operations": 0,
            "priority": 3,
            "machine_seq": [
                0,
                3,
                4,
                6,
                5
            ],
            "current_operation": 0
        },
        {
            "job_id": 11,
            "operations": [
                {
                    "job_id": 11,
                    "op_id": 0,
                    "machine": 2,
                    "processing_time": 6.625798909370035,
                    "setup_time": 0.0,
                    "status": "pending"
                },
                {
                    "job_id": 11,
                    "op_id": 1,
                    "machine": 9,
                    "processing_time": 6.881322500881612,
                    "setup_time": 1.7714693493796299,
                    "status": "pending"
                },
                {
                    "job_id": 11,
                    "op_id": 2,
                    "machine": 3,
                    "processing_time": 11.063077308535108,
                    "setup_time": 1.586797185792566,
                    "status": "pending"
                },
                {
                    "job_id": 11,
                    "op_id": 3,
                    "machine": 3,
                    "processing_time": 7.949346340147606,
                    "setup_time": 1.948427796538161,
                    "status": "pending"
                }
            ],
            "arrival_time": 5,
            "completed_operations": 0,
            "priority": 3,
            "machine_seq": [
                2,
                9,
                3,
                3
            ],
            "current_operation": 0
        },
        {
            "job_id": 12,
            "operations": [
                {
                    "job_id": 12,
                    "op_id": 0,
                    "machine": 0,
                    "processing_time": 11.90488808929547,
                    "setup_time": 0.0,
                    "status": "pending"
                },
                {
                    "job_id": 12,
                    "op_id": 1,
                    "machine": 8,
                    "processing_time": 14.368713588059888,
                    "setup_time": 0.8410318337414808,
                    "status": "pending"
                },
                {
                    "job_id": 12,
                    "op_id": 2,
                    "machine": 4,
                    "processing_time": 6.014906591616094,
                    "setup_time": 2.3528852498523634,
                    "status": "pending"
                },
                {
                    "job_id": 12,
                    "op_id": 3,
                    "machine": 5,
                    "processing_time": 11.693175150585054,
                    "setup_time": 1.0955654327997353,
                    "status": "pending"
                },
                {
                    "job_id": 12,
                    "op_id": 4,
                    "machine": 3,
                    "processing_time": 3.2422588336305505,
                    "setup_time": 1.5847094520483496,
                    "status": "pending"
                },
                {
                    "job_id": 12,
                    "op_id": 5,
                    "machine": 5,
                    "processing_time": 14.849184342189403,
                    "setup_time": 0.7268809920984405,
                    "status": "pending"
                }
            ],
            "arrival_time": 45,
            "completed_operations": 0,
            "priority": 3,
            "machine_seq": [
                0,
                8,
                4,
                5,
                3,
                5
            ],
            "current_operation": 0
        },
        {
            "job_id": 13,
            "operations": [
                {
                    "job_id": 13,
                    "op_id": 0,
                    "machine": 4,
                    "processing_time": 10.267985289403498,
                    "setup_time": 0.0,
                    "status": "pending"
                },
                {
                    "job_id": 13,
                    "op_id": 1,
                    "machine": 5,
                    "processing_time": 8.78840964056476,
                    "setup_time": 1.1004772024908063,
                    "status": "pending"
                },
                {
                    "job_id": 13,
                    "op_id": 2,
                    "machine": 8,
                    "processing_time": 10.41546097780373,
                    "setup_time": 2.7261498647222524,
                    "status": "pending"
                },
                {
                    "job_id": 13,
                    "op_id": 3,
                    "machine": 5,
                    "processing_time": 10.907843908744253,
                    "setup_time": 0.8579744798741172,
                    "status": "pending"
                }
            ],
            "arrival_time": 39,
            "completed_operations": 0,
            "priority": 5,
            "machine_seq": [
                4,
                5,
                8,
                5
            ],
            "current_operation": 0
        },
        {
            "job_id": 14,
            "operations": [
                {
                    "job_id": 14,
                    "op_id": 0,
                    "machine": 9,
                    "processing_time": 18.471525201219873,
                    "setup_time": 0.0,
                    "status": "pending"
                },
                {
                    "job_id": 14,
                    "op_id": 1,
                    "machine": 7,
                    "processing_time": 8.608713737889996,
                    "setup_time": 0.23966912128689244,
                    "status": "pending"
                },
                {
                    "job_id": 14,
                    "op_id": 2,
                    "machine": 3,
                    "processing_time": 8.97387691065815,
                    "setup_time": 0.47356502853578264,
                    "status": "pending"
                },
                {
                    "job_id": 14,
                    "op_id": 3,
                    "machine": 8,
                    "processing_time": 7.024450418160753,
                    "setup_time": 2.1914262300718534,
                    "status": "pending"
                },
                {
                    "job_id": 14,
                    "op_id": 4,
                    "machine": 8,
                    "processing_time": 12.162363601663593,
                    "setup_time": 2.933756550255443,
                    "status": "pending"
                },
                {
                    "job_id": 14,
                    "op_id": 5,
                    "machine": 4,
                    "processing_time": 4.573136050336155,
                    "setup_time": 2.932928066095201,
                    "status": "pending"
                }
            ],
            "arrival_time": 43,
            "completed_operations": 0,
            "priority": 1,
            "machine_seq": [
                9,
                7,
                3,
                8,
                8,
                4
            ],
            "current_operation": 0
        },
        {
            "job_id": 15,
            "operations": [
                {
                    "job_id": 15,
                    "op_id": 0,
                    "machine": 0,
                    "processing_time": 15.536314724640153,
                    "setup_time": 0.0,
                    "status": "pending"
                },
                {
                    "job_id": 15,
                    "op_id": 1,
                    "machine": 9,
                    "processing_time": 11.05247778941161,
                    "setup_time": 1.065312227410837,
                    "status": "pending"
                },
                {
                    "job_id": 15,
                    "op_id": 2,
                    "machine": 5,
                    "processing_time": 12.667663596750593,
                    "setup_time": 1.6722972854414286,
                    "status": "pending"
                }
            ],
            "arrival_time": 34,
            "completed_operations": 0,
            "priority": 2,
            "machine_seq": [
                0,
                9,
                5
            ],
            "current_operation": 0
        },
        {
            "job_id": 16,
            "operations": [
                {
                    "job_id": 16,
                    "op_id": 0,
                    "machine": 2,
                    "processing_time": 4.938864842644548,
                    "setup_time": 0.0,
                    "status": "pending"
                },
                {
                    "job_id": 16,
                    "op_id": 1,
                    "machine": 7,
                    "processing_time": 12.37131312836745,
                    "setup_time": 1.386333942972572,
                    "status": "pending"
                },
                {
                    "job_id": 16,
                    "op_id": 2,
                    "machine": 3,
                    "processing_time": 11.317559060261647,
                    "setup_time": 1.222512175485933,
                    "status": "pending"
                }
            ],
            "arrival_time": 18,
            "completed_operations": 0,
            "priority": 3,
            "machine_seq": [
                2,
                7,
                3
            ],
            "current_operation": 0
        },
        {
            "job_id": 17,
            "operations": [
                {
                    "job_id": 17,
                    "op_id": 0,
                    "machine": 3,
                    "processing_time": 17.779209082473237,
                    "setup_time": 0.0,
                    "status": "pending"
                },
                {
                    "job_id": 17,
                    "op_id": 1,
                    "machine": 3,
                    "processing_time": 7.98215396517498,
                    "setup_time": 0.31192731225873394,
                    "status": "pending"
                },
                {
                    "job_id": 17,
                    "op_id": 2,
                    "machine": 1,
                    "processing_time": 11.844188944151771,
                    "setup_time": 2.4914571007362722,
                    "status": "pending"
                },
                {
                    "job_id": 17,
                    "op_id": 3,
                    "machine": 6,
                    "processing_time": 11.727153004998103,
                    "setup_time": 2.010260556323547,
                    "status": "pending"
                }
            ],
            "arrival_time": 21,
            "completed_operations": 0,
            "priority": 2,
            "machine_seq": [
                3,
                3,
                1,
                6
            ],
            "current_operation": 0
        },
        {
            "job_id": 18,
            "operations": [
                {
                    "job_id": 18,
                    "op_id": 0,
                    "machine": 1,
                    "processing_time": 6.666708067500944,
                    "setup_time": 0.0,
                    "status": "pending"
                },
                {
                    "job_id": 18,
                    "op_id": 1,
                    "machine": 3,
                    "processing_time": 11.234206754176808,
                    "setup_time": 1.247847832408822,
                    "status": "pending"
                },
                {
                    "job_id": 18,
                    "op_id": 2,
                    "machine": 4,
                    "processing_time": 18.835796975518505,
                    "setup_time": 1.2027409746170994,
                    "status": "pending"
                },
                {
                    "job_id": 18,
                    "op_id": 3,
                    "machine": 4,
                    "processing_time": 14.557632809238823,
                    "setup_time": 2.018385712342303,
                    "status": "pending"
                },
                {
                    "job_id": 18,
                    "op_id": 4,
                    "machine": 7,
                    "processing_time": 8.990029152415168,
                    "setup_time": 1.4677335225289176,
                    "status": "pending"
                }
            ],
            "arrival_time": 17,
            "completed_operations": 0,
            "priority": 4,
            "machine_seq": [
                1,
                3,
                4,
                4,
                7
            ],
            "current_operation": 0
        },
        {
            "job_id": 19,
            "operations": [
                {
                    "job_id": 19,
                    "op_id": 0,
                    "machine": 8,
                    "processing_time": 17.322811551297153,
                    "setup_time": 0.0,
                    "status": "pending"
                },
                {
                    "job_id": 19,
                    "op_id": 1,
                    "machine": 5,
                    "processing_time": 19.276263555873285,
                    "setup_time": 1.7423458662236162,
                    "status": "pending"
                },
                {
                    "job_id": 19,
                    "op_id": 2,
                    "machine": 0,
                    "processing_time": 15.185806421665367,
                    "setup_time": 1.3190615518905995,
                    "status": "pending"
                }
            ],
            "arrival_time": 19,
            "completed_operations": 0,
            "priority": 5,
            "machine_seq": [
                8,
                5,
                0
            ],
            "current_operation": 0
        },
        {
            "job_id": 20,
            "operations": [
                {
                    "job_id": 20,
                    "op_id": 0,
                    "machine": 9,
                    "processing_time": 16.45901251484026,
                    "setup_time": 0.0,
                    "status": "pending"
                },
                {
                    "job_id": 20,
                    "op_id": 1,
                    "machine": 3,
                    "processing_time": 16.43003503563143,
                    "setup_time": 1.4221392871343597,
                    "status": "pending"
                },
                {
                    "job_id": 20,
                    "op_id": 2,
                    "machine": 2,
                    "processing_time": 7.838717250974476,
                    "setup_time": 1.8008555360481395,
                    "status": "pending"
                },
                {
                    "job_id": 20,
                    "op_id": 3,
                    "machine": 3,
                    "processing_time": 7.040867542091848,
                    "setup_time": 0.7564872605922163,
                    "status": "pending"
                }
            ],
            "arrival_time": 38,
            "completed_operations": 0,
            "priority": 2,
            "machine_seq": [
                9,
                3,
                2,
                3
            ],
            "current_operation": 0
        },
        {
            "job_id": 21,
            "operations": [
                {
                    "job_id": 21,
                    "op_id": 0,
                    "machine": 0,
                    "processing_time": 18.185209486753774,
                    "setup_time": 0.0,
                    "status": "pending"
                },
                {
                    "job_id": 21,
                    "op_id": 1,
                    "machine": 8,
                    "processing_time": 8.891357998342157,
                    "setup_time": 2.1615830860763525,
                    "status": "pending"
                },
                {
                    "job_id": 21,
                    "op_id": 2,
                    "machine": 0,
                    "processing_time": 13.419053371692716,
                    "setup_time": 2.112617810499099,
                    "status": "pending"
                }
            ],
            "arrival_time": 22,
            "completed_operations": 0,
            "priority": 1,
            "machine_seq": [
                0,
                8,
                0
            ],
            "current_operation": 0
        },
        {
            "job_id": 22,
            "operations": [
                {
                    "job_id": 22,
                    "op_id": 0,
                    "machine": 1,
                    "processing_time": 10.986508102329386,
                    "setup_time": 0.0,
                    "status": "pending"
                },
                {
                    "job_id": 22,
                    "op_id": 1,
                    "machine": 5,
                    "processing_time": 16.854269915083062,
                    "setup_time": 1.9206936223512585,
                    "status": "pending"
                },
                {
                    "job_id": 22,
                    "op_id": 2,
                    "machine": 2,
                    "processing_time": 18.56295817686858,
                    "setup_time": 2.982800786965675,
                    "status": "pending"
                },
                {
                    "job_id": 22,
                    "op_id": 3,
                    "machine": 0,
                    "processing_time": 11.272715236101625,
                    "setup_time": 0.6987830171179976,
                    "status": "pending"
                },
                {
                    "job_id": 22,
                    "op_id": 4,
                    "machine": 8,
                    "processing_time": 7.055496710085441,
                    "setup_time": 1.7738423706521227,
                    "status": "pending"
                },
                {
                    "job_id": 22,
                    "op_id": 5,
                    "machine": 5,
                    "processing_time": 11.028809468916386,
                    "setup_time": 2.84166504375903,
                    "status": "pending"
                }
            ],
            "arrival_time": 44,
            "completed_operations": 0,
            "priority": 5,
            "machine_seq": [
                1,
                5,
                2,
                0,
                8,
                5
            ],
            "current_operation": 0
        },
        {
            "job_id": 23,
            "operations": [
                {
                    "job_id": 23,
                    "op_id": 0,
                    "machine": 3,
                    "processing_time": 10.31369378468602,
                    "setup_time": 0.0,
                    "status": "pending"
                },
                {
                    "job_id": 23,
                    "op_id": 1,
                    "machine": 0,
                    "processing_time": 8.265718606072584,
                    "setup_time": 0.8005000319074878,
                    "status": "pending"
                },
                {
                    "job_id": 23,
                    "op_id": 2,
                    "machine": 2,
                    "processing_time": 16.85572055014307,
                    "setup_time": 2.909900544160998,
                    "status": "pending"
                },
                {
                    "job_id": 23,
                    "op_id": 3,
                    "machine": 2,
                    "processing_time": 7.366678507561301,
                    "setup_time": 2.316593206516603,
                    "status": "pending"
                },
                {
                    "job_id": 23,
                    "op_id": 4,
                    "machine": 8,
                    "processing_time": 12.160199802694184,
                    "setup_time": 0.19742250095412717,
                    "status": "pending"
                },
                {
                    "job_id": 23,
                    "op_id": 5,
                    "machine": 1,
                    "processing_time": 14.031256300037306,
                    "setup_time": 0.40273603986553286,
                    "status": "pending"
                }
            ],
            "arrival_time": 39,
            "completed_operations": 0,
            "priority": 4,
            "machine_seq": [
                3,
                0,
                2,
                2,
                8,
                1
            ],
            "current_operation": 0
        },
        {
            "job_id": 24,
            "operations": [
                {
                    "job_id": 24,
                    "op_id": 0,
                    "machine": 7,
                    "processing_time": 16.876991753642546,
                    "setup_time": 0.0,
                    "status": "pending"
                },
                {
                    "job_id": 24,
                    "op_id": 1,
                    "machine": 4,
                    "processing_time": 8.773285622843419,
                    "setup_time": 2.9392350959354556,
                    "status": "pending"
                },
                {
                    "job_id": 24,
                    "op_id": 2,
                    "machine": 8,
                    "processing_time": 6.589451717328563,
                    "setup_time": 1.4746894929682015,
                    "status": "pending"
                },
                {
                    "job_id": 24,
                    "op_id": 3,
                    "machine": 6,
                    "processing_time": 10.930985906617494,
                    "setup_time": 0.46263620527028915,
                    "status": "pending"
                },
                {
                    "job_id": 24,
                    "op_id": 4,
                    "machine": 3,
                    "processing_time": 11.563295802805888,
                    "setup_time": 1.2663901311783228,
                    "status": "pending"
                },
                {
                    "job_id": 24,
                    "op_id": 5,
                    "machine": 8,
                    "processing_time": 19.450908871521584,
                    "setup_time": 2.4377589590730295,
                    "status": "pending"
                }
            ],
            "arrival_time": 20,
            "completed_operations": 0,
            "priority": 4,
            "machine_seq": [
                7,
                4,
                8,
                6,
                3,
                8
            ],
            "current_operation": 0
        }
    ],
    "machines": [
        {
            "machine_id": 0,
            "status": "available",
            "current_job": null,
            "next_available_time": 0,
            "type": "special"
        },
        {
            "machine_id": 1,
            "status": "available",
            "current_job": null,
            "next_available_time": 0,
            "type": "special"
        },
        {
            "machine_id": 2,
            "status": "available",
            "current_job": null,
            "next_available_time": 0,
            "type": "special"
        },
        {
            "machine_id": 3,
            "status": "available",
            "current_job": null,
            "next_available_time": 0,
            "type": "special"
        },
        {
            "machine_id": 4,
            "status": "available",
            "current_job": null,
            "next_available_time": 0,
            "type": "general"
        },
        {
            "machine_id": 5,
            "status": "available",
            "current_job": null,
            "next_available_time": 0,
            "type": "special"
        },
        {
            "machine_id": 6,
            "status": "available",
            "current_job": null,
            "next_available_time": 0,
            "type": "special"
        },
        {
            "machine_id": 7,
            "status": "available",
            "current_job": null,
            "next_available_time": 0,
            "type": "special"
        },
        {
            "machine_id": 8,
            "status": "available",
            "current_job": null,
            "next_available_time": 0,
            "type": "general"
        },
        {
            "machine_id": 9,
            "status": "available",
            "current_job": null,
            "next_available_time": 0,
            "type": "general"
        }
    ],
    "resources": {
        "resource_capacity": 6,
        "machines": [
            {
                "machine_id": 8,
                "status": "available",
                "current_job": null,
                "next_available_time": 0,
                "type": "general"
            },
            {
                "machine_id": 9,
                "status": "available",
                "current_job": null,
                "next_available_time": 0,
                "type": "general"
            },
            {
                "machine_id": 4,
                "status": "available",
                "current_job": null,
                "next_available_time": 0,
                "type": "general"
            },
            {
                "machine_id": 0,
                "status": "available",
                "current_job": null,
                "next_available_time": 0,
                "type": "special"
            },
            {
                "machine_id": 1,
                "status": "available",
                "current_job": null,
                "next_available_time": 0,
                "type": "special"
            },
            {
                "machine_id": 2,
                "status": "available",
                "current_job": null,
                "next_available_time": 0,
                "type": "special"
            }
        ]
    }
}