{
    "jobs": [
        {
            "job_id": 0,
            "operations": [
                {
                    "job_id": 0,
                    "op_id": 0,
                    "machine": 6,
                    "processing_time": 7.678781060895593,
                    "setup_time": 0.0,
                    "status": "pending"
                },
                {
                    "job_id": 0,
                    "op_id": 1,
                    "machine": 1,
                    "processing_time": 18.11560730982946,
                    "setup_time": 0.5758360456907271,
                    "status": "pending"
                },
                {
                    "job_id": 0,
                    "op_id": 2,
                    "machine": 4,
                    "processing_time": 14.394531233188848,
                    "setup_time": 1.4173306635195932,
                    "status": "pending"
                },
                {
                    "job_id": 0,
                    "op_id": 3,
                    "machine": 6,
                    "processing_time": 9.336821739017104,
                    "setup_time": 0.6022127751018207,
                    "status": "pending"
                },
                {
                    "job_id": 0,
                    "op_id": 4,
                    "machine": 7,
                    "processing_time": 12.137132540733685,
                    "setup_time": 1.8526447301676043,
                    "status": "pending"
                }
            ],
            "arrival_time": 31,
            "completed_operations": 0,
            "priority": 2,
            "machine_seq": [
                6,
                1,
                4,
                6,
                7
            ],
            "current_operation": 0
        },
        {
            "job_id": 1,
            "operations": [
                {
                    "job_id": 1,
                    "op_id": 0,
                    "machine": 3,
                    "processing_time": 10.10583624236599,
                    "setup_time": 0.0,
                    "status": "pending"
                },
                {
                    "job_id": 1,
                    "op_id": 1,
                    "machine": 7,
                    "processing_time": 13.84453177085009,
                    "setup_time": 0.46795908573163314,
                    "status": "pending"
                },
                {
                    "job_id": 1,
                    "op_id": 2,
                    "machine": 7,
                    "processing_time": 6.135637466989765,
                    "setup_time": 1.0950467503907522,
                    "status": "pending"
                },
                {
                    "job_id": 1,
                    "op_id": 3,
                    "machine": 7,
                    "processing_time": 7.045886696904234,
                    "setup_time": 1.699458337395186,
                    "status": "pending"
                },
                {
                    "job_id": 1,
                    "op_id": 4,
                    "machine": 6,
                    "processing_time": 17.34575095404732,
                    "setup_time": 2.30644912573864,
                    "status": "pending"
                }
            ],
            "arrival_time": 38,
            "completed_operations": 0,
            "priority": 1,
            "machine_seq": [
                3,
                7,
                7,
                7,
                6
            ],
            "current_operation": 0
        },
        {
            "job_id": 2,
            "operations": [
                {
                    "job_id": 2,
                    "op_id": 0,
                    "machine": 2,
                    "processing_time": 10.682096697223994,
                    "setup_time": 0.0,
                    "status": "pending"
                },
                {
                    "job_id": 2,
                    "op_id": 1,
                    "machine": 7,
                    "processing_time": 12.785778035681552,
                    "setup_time": 2.3387694571687496,
                    "status": "pending"
                },
                {
                    "job_id": 2,
                    "op_id": 2,
                    "machine": 2,
                    "processing_time": 8.658680600710369,
                    "setup_time": 0.802245112956603,
                    "status": "pending"
                },
                {
                    "job_id": 2,
                    "op_id": 3,
                    "machine": 2,
                    "processing_time": 17.523479089127267,
                    "setup_time": 1.6885870902831763,
                    "status": "pending"
                },
                {
                    "job_id": 2,
                    "op_id": 4,
                    "machine": 3,
                    "processing_time": 8.590414812145504,
                    "setup_time": 0.0317359358679975,
                    "status": "pending"
                },
                {
                    "job_id": 2,
                    "op_id": 5,
                    "machine": 7,
                    "processing_time": 13.12802282020243,
                    "setup_time": 0.6921488208790858,
                    "status": "pending"
                }
            ],
            "arrival_time": 37,
            "completed_operations": 0,
            "priority": 5,
            "machine_seq": [
                2,
                7,
                2,
                2,
                3,
                7
            ],
            "current_operation": 0
        },
        {
            "job_id": 3,
            "operations": [
                {
                    "job_id": 3,
                    "op_id": 0,
                    "machine": 6,
                    "processing_time": 16.0560413784769,
                    "setup_time": 0.0,
                    "status": "pending"
                },
                {
                    "job_id": 3,
                    "op_id": 1,
                    "machine": 5,
                    "processing_time": 13.835200037410388,
                    "setup_time": 1.2101557195172825,
                    "status": "pending"
                },
                {
                    "job_id": 3,
                    "op_id": 2,
                    "machine": 8,
                    "processing_time": 9.796125231727334,
                    "setup_time": 0.5410819739807611,
                    "status": "pending"
                }
            ],
            "arrival_time": 38,
            "completed_operations": 0,
            "priority": 2,
            "machine_seq": [
                6,
                5,
                8
            ],
            "current_operation": 0
        },
        {
            "job_id": 4,
            "operations": [
                {
                    "job_id": 4,
                    "op_id": 0,
                    "machine": 2,
                    "processing_time": 8.498932205756887,
                    "setup_time": 0.0,
                    "status": "pending"
                },
                {
                    "job_id": 4,
                    "op_id": 1,
                    "machine": 5,
                    "processing_time": 10.739569197815378,
                    "setup_time": 2.595158679435962,
                    "status": "pending"
                },
                {
                    "job_id": 4,
                    "op_id": 2,
                    "machine": 2,
                    "processing_time": 11.358224372600606,
                    "setup_time": 1.2953685280529523,
                    "status": "pending"
                },
                {
                    "job_id": 4,
                    "op_id": 3,
                    "machine": 8,
                    "processing_time": 9.663795971319917,
                    "setup_time": 1.3960422630201783,
                    "status": "pending"
                },
                {
                    "job_id": 4,
                    "op_id": 4,
                    "machine": 5,
                    "processing_time": 9.942822106676658,
                    "setup_time": 0.6156648061960643,
                    "status": "pending"
                },
                {
                    "job_id": 4,
                    "op_id": 5,
                    "machine": 3,
                    "processing_time": 12.702213194188229,
                    "setup_time": 1.4075451068623548,
                    "status": "pending"
                },
                {
                    "job_id": 4,
                    "op_id": 6,
                    "machine": 1,
                    "processing_time": 9.7102222694485,
                    "setup_time": 1.5230273633073352,
                    "status": "pending"
                },
                {
                    "job_id": 4,
                    "op_id": 7,
                    "machine": 7,
                    "processing_time": 10.677022867557188,
                    "setup_time": 2.836001260320268,
                    "status": "pending"
                }
            ],
            "arrival_time": 24,
            "completed_operations": 0,
            "priority": 4,
            "machine_seq": [
                2,
                5,
                2,
                8,
                5,
                3,
                1,
                7
            ],
            "current_operation": 0
        },
        {
            "job_id": 5,
            "operations": [
                {
                    "job_id": 5,
                    "op_id": 0,
                    "machine": 7,
                    "processing_time": 7.448557622103313,
                    "setup_time": 0.0,
                    "status": "pending"
                },
                {
                    "job_id": 5,
                    "op_id": 1,
                    "machine": 6,
                    "processing_time": 12.876309542136669,
                    "setup_time": 1.7960208524657675,
                    "status": "pending"
                },
                {
                    "job_id": 5,
                    "op_id": 2,
                    "machine": 9,
                    "processing_time": 9.55974712389808,
                    "setup_time": 2.883873299282576,
                    "status": "pending"
                },
                {
                    "job_id": 5,
                    "op_id": 3,
                    "machine": 6,
                    "processing_time": 16.256628838860156,
                    "setup_time": 2.710484410095572,
                    "status": "pending"
                },
                {
                    "job_id": 5,
                    "op_id": 4,
                    "machine": 4,
                    "processing_time": 11.60684501994121,
                    "setup_time": 1.1302467965172736,
                    "status": "pending"
                }
            ],
            "arrival_time": 6,
            "completed_operations": 0,
            "priority": 1,
            "machine_seq": [
                7,
                6,
                9,
                6,
                4
            ],
            "current_operation": 0
        },
        {
            "job_id": 6,
            "operations": [
                {
                    "job_id": 6,
                    "op_id": 0,
                    "machine": 8,
                    "processing_time": 14.305259139074174,
                    "setup_time": 0.0,
                    "status": "pending"
                },
                {
                    "job_id": 6,
                    "op_id": 1,
                    "machine": 8,
                    "processing_time": 8.832779424555124,
                    "setup_time": 0.9721104320813423,
                    "status": "pending"
                },
                {
                    "job_id": 6,
                    "op_id": 2,
                    "machine": 8,
                    "processing_time": 6.136347894963006,
                    "setup_time": 1.40334033754622,
                    "status": "pending"
                },
                {
                    "job_id": 6,
                    "op_id": 3,
                    "machine": 3,
                    "processing_time": 13.601664831369469,
                    "setup_time": 2.1522471350970473,
                    "status": "pending"
                },
                {
                    "job_id": 6,
                    "op_id": 4,
                    "machine": 3,
                    "processing_time": 12.248105157078445,
                    "setup_time": 2.899954159431782,
                    "status": "pending"
                },
                {
                    "job_id": 6,
                    "op_id": 5,
                    "machine": 8,
                    "processing_time": 13.097780201317256,
                    "setup_time": 0.6722038004556561,
                    "status": "pending"
                }
            ],
            "arrival_time": 34,
            "completed_operations": 0,
            "priority": 1,
            "machine_seq": [
                8,
                8,
                8,
                3,
                3,
                8
            ],
            "current_operation": 0
        },
        {
            "job_id": 7,
            "operations": [
                {
                    "job_id": 7,
                    "op_id": 0,
                    "machine": 1,
                    "processing_time": 13.321112621154041,
                    "setup_time": 0.0,
                    "status": "pending"
                },
                {
                    "job_id": 7,
                    "op_id": 1,
                    "machine": 2,
                    "processing_time": 11.018065358270519,
                    "setup_time": 2.199307389750052,
                    "status": "pending"
                },
                {
                    "job_id": 7,
                    "op_id": 2,
                    "machine": 2,
                    "processing_time": 7.817049372168858,
                    "setup_time": 1.339445143671576,
                    "status": "pending"
                }
            ],
            "arrival_time": 7,
            "completed_operations": 0,
            "priority": 3,
            "machine_seq": [
                1,
                2,
                2
            ],
            "current_operation": 0
        },
        {
            "job_id": 8,
            "operations": [
                {
                    "job_id": 8,
                    "op_id": 0,
                    "machine": 3,
                    "processing_time": 12.413828165509855,
                    "setup_time": 0.0,
                    "status": "pending"
                },
                {
                    "job_id": 8,
                    "op_id": 1,
                    "machine": 2,
                    "processing_time": 13.059299546042425,
                    "setup_time": 2.9162055526880835,
                    "status": "pending"
                },
                {
                    "job_id": 8,
                    "op_id": 2,
                    "machine": 3,
                    "processing_time": 6.3487964372662296,
                    "setup_time": 0.7171643125512165,
                    "status": "pending"
                },
                {
                    "job_id": 8,
                    "op_id": 3,
                    "machine": 0,
                    "processing_time": 7.886540807342618,
                    "setup_time": 1.8872609252601902,
                    "status": "pending"
                },
                {
                    "job_id": 8,
                    "op_id": 4,
                    "machine": 3,
                    "processing_time": 9.941730779980531,
                    "setup_time": 2.8633109861032597,
                    "status": "pending"
                },
                {
                    "job_id": 8,
                    "op_id": 5,
                    "machine": 7,
                    "processing_time": 8.57326837984516,
                    "setup_time": 2.777512405842123,
                    "status": "pending"
                }
            ],
            "arrival_time": 33,
            "completed_operations": 0,
            "priority": 4,
            "machine_seq": [
                3,
                2,
                3,
                0,
                3,
                7
            ],
            "current_operation": 0
        },
        {
            "job_id": 9,
            "operations": [
                {
                    "job_id": 9,
                    "op_id": 0,
                    "machine": 7,
                    "processing_time": 10.009363080649909,
                    "setup_time": 0.0,
                    "status": "pending"
                },
                {
                    "job_id": 9,
                    "op_id": 1,
                    "machine": 3,
                    "processing_time": 13.543657912446928,
                    "setup_time": 2.6685511197727956,
                    "status": "pending"
                },
                {
                    "job_id": 9,
                    "op_id": 2,
                    "machine": 6,
                    "processing_time": 16.561462801351038,
                    "setup_time": 0.5971250402518955,
                    "status": "pending"
                },
                {
                    "job_id": 9,
                    "op_id": 3,
                    "machine": 5,
                    "processing_time": 18.886288719291798,
                    "setup_time": 2.5513548717903616,
                    "status": "pending"
                }
            ],
            "arrival_time": 4,
            "completed_operations": 0,
            "priority": 4,
            "machine_seq": [
                7,
                3,
                6,
                5
            ],
            "current_operation": 0
        },
        {
            "job_id": 10,
            "operations": [
                {
                    "job_id": 10,
                    "op_id": 0,
                    "machine": 5,
                    "processing_time": 11.602659477266325,
                    "setup_time": 0.0,
                    "status": "pending"
                },
                {
                    "job_id": 10,
                    "op_id": 1,
                    "machine": 7,
                    "processing_time": 10.573002888023536,
                    "setup_time": 1.7243074807165764,
                    "status": "pending"
                },
                {
                    "job_id": 10,
                    "op_id": 2,
                    "machine": 3,
                    "processing_time": 7.800877493608864,
                    "setup_time": 0.9201355958019429,
                    "status": "pending"
                },
                {
                    "job_id": 10,
                    "op_id": 3,
                    "machine": 4,
                    "processing_time": 10.890601050231664,
                    "setup_time": 0.1851594426692914,
                    "status": "pending"
                },
                {
                    "job_id": 10,
                    "op_id": 4,
                    "machine": 3,
                    "processing_time": 8.964146772350425,
                    "setup_time": 1.1447329916026492,
                    "status": "pending"
                },
                {
                    "job_id": 10,
                    "op_id": 5,
                    "machine": 2,
                    "processing_time": 4.1480931031943085,
                    "setup_time": 1.8719470680046182,
                    "status": "pending"
                },
                {
                    "job_id": 10,
                    "op_id": 6,
                    "machine": 6,
                    "processing_time": 7.179862103062129,
                    "setup_time": 2.858264488272636,
                    "status": "pending"
                },
                {
                    "job_id": 10,
                    "op_id": 7,
                    "machine": 0,
                    "processing_time": 7.491092350832257,
                    "setup_time": 0.6455119986656672,
                    "status": "pending"
                }
            ],
            "arrival_time": 46,
            "completed_operations": 0,
            "priority": 5,
            "machine_seq": [
                5,
                7,
                3,
                4,
                3,
                2,
                6,
                0
            ],
            "current_operation": 0
        },
        {
            "job_id": 11,
            "operations": [
                {
                    "job_id": 11,
                    "op_id": 0,
                    "machine": 1,
                    "processing_time": 9.552348320517146,
                    "setup_time": 0.0,
                    "status": "pending"
                },
                {
                    "job_id": 11,
                    "op_id": 1,
                    "machine": 4,
                    "processing_time": 8.093497655221746,
                    "setup_time": 2.988998685610831,
                    "status": "pending"
                },
                {
                    "job_id": 11,
                    "op_id": 2,
                    "machine": 5,
                    "processing_time": 10.019197180886197,
                    "setup_time": 1.4346963059690645,
                    "status": "pending"
                },
                {
                    "job_id": 11,
                    "op_id": 3,
                    "machine": 4,
                    "processing_time": 12.690284006396498,
                    "setup_time": 2.7516376629757637,
                    "status": "pending"
                },
                {
                    "job_id": 11,
                    "op_id": 4,
                    "machine": 7,
                    "processing_time": 16.3010365093151,
                    "setup_time": 1.1569762648759894,
                    "status": "pending"
                },
                {
                    "job_id": 11,
                    "op_id": 5,
                    "machine": 7,
                    "processing_time": 13.107230462964957,
                    "setup_time": 1.4664851483880406,
                    "status": "pending"
                }
            ],
            "arrival_time": 48,
            "completed_operations": 0,
            "priority": 5,
            "machine_seq": [
                1,
                4,
                5,
                4,
                7,
                7
            ],
            "current_operation": 0
        },
        {
            "job_id": 12,
            "operations": [
                {
                    "job_id": 12,
                    "op_id": 0,
                    "machine": 2,
                    "processing_time": 7.313146837891018,
                    "setup_time": 0.0,
                    "status": "pending"
                },
                {
                    "job_id": 12,
                    "op_id": 1,
                    "machine": 3,
                    "processing_time": 11.8507728128487,
                    "setup_time": 0.8566900430482212,
                    "status": "pending"
                },
                {
                    "job_id": 12,
                    "op_id": 2,
                    "machine": 7,
                    "processing_time": 14.91878295092362,
                    "setup_time": 1.0771244709917291,
                    "status": "pending"
                },
                {
                    "job_id": 12,
                    "op_id": 3,
                    "machine": 1,
                    "processing_time": 14.531266470812998,
                    "setup_time": 0.9867969415404556,
                    "status": "pending"
                },
                {
                    "job_id": 12,
                    "op_id": 4,
                    "machine": 1,
                    "processing_time": 15.36443367858222,
                    "setup_time": 0.06456592500970249,
                    "status": "pending"
                },
                {
                    "job_id": 12,
                    "op_id": 5,
                    "machine": 7,
                    "processing_time": 11.047952901403672,
                    "setup_time": 1.994665717134306,
                    "status": "pending"
                },
                {
                    "job_id": 12,
                    "op_id": 6,
                    "machine": 3,
                    "processing_time": 8.391245248029803,
                    "setup_time": 0.766127428380965,
                    "status": "pending"
                },
                {
                    "job_id": 12,
                    "op_id": 7,
                    "machine": 0,
                    "processing_time": 4.990716163487412,
                    "setup_time": 0.27551480788344607,
                    "status": "pending"
                }
            ],
            "arrival_time": 39,
            "completed_operations": 0,
            "priority": 1,
            "machine_seq": [
                2,
                3,
                7,
                1,
                1,
                7,
                3,
                0
            ],
            "current_operation": 0
        },
        {
            "job_id": 13,
            "operations": [
                {
                    "job_id": 13,
                    "op_id": 0,
                    "machine": 9,
                    "processing_time": 6.262998941103957,
                    "setup_time": 0.0,
                    "status": "pending"
                },
                {
                    "job_id": 13,
                    "op_id": 1,
                    "machine": 1,
                    "processing_time": 12.629843336846521,
                    "setup_time": 2.682675563791978,
                    "status": "pending"
                },
                {
                    "job_id": 13,
                    "op_id": 2,
                    "machine": 9,
                    "processing_time": 13.014643573752387,
                    "setup_time": 0.3712834715626093,
                    "status": "pending"
                },
                {
                    "job_id": 13,
                    "op_id": 3,
                    "machine": 3,
                    "processing_time": 12.712741400887088,
                    "setup_time": 1.3932794239606205,
                    "status": "pending"
                },
                {
                    "job_id": 13,
                    "op_id": 4,
                    "machine": 2,
                    "processing_time": 6.557669461303365,
                    "setup_time": 1.2203622192552428,
                    "status": "pending"
                },
                {
                    "job_id": 13,
                    "op_id": 5,
                    "machine": 4,
                    "processing_time": 9.315448495842748,
                    "setup_time": 1.4746928431403552,
                    "status": "pending"
                },
                {
                    "job_id": 13,
                    "op_id": 6,
                    "machine": 7,
                    "processing_time": 8.52401171915392,
                    "setup_time": 2.3754094431742785,
                    "status": "pending"
                },
                {
                    "job_id": 13,
                    "op_id": 7,
                    "machine": 2,
                    "processing_time": 2.801214207983005,
                    "setup_time": 2.3100158937597928,
                    "status": "pending"
                }
            ],
            "arrival_time": 30,
            "completed_operations": 0,
            "priority": 2,
            "machine_seq": [
                9,
                1,
                9,
                3,
                2,
                4,
                7,
                2
            ],
            "current_operation": 0
        },
        {
            "job_id": 14,
            "operations": [
                {
                    "job_id": 14,
                    "op_id": 0,
                    "machine": 3,
                    "processing_time": 14.437552962590194,
                    "setup_time": 0.0,
                    "status": "pending"
                },
                {
                    "job_id": 14,
                    "op_id": 1,
                    "machine": 5,
                    "processing_time": 9.480594254365629,
                    "setup_time": 0.4392292189128325,
                    "status": "pending"
                },
                {
                    "job_id": 14,
                    "op_id": 2,
                    "machine": 0,
                    "processing_time": 17.575634757097355,
                    "setup_time": 2.3191089914363756,
                    "status": "pending"
                },
                {
                    "job_id": 14,
                    "op_id": 3,
                    "machine": 4,
                    "processing_time": 14.16702833841077,
                    "setup_time": 0.07685802996957847,
                    "status": "pending"
                },
                {
                    "job_id": 14,
                    "op_id": 4,
                    "machine": 1,
                    "processing_time": 7.4373406270513085,
                    "setup_time": 1.35220533007266,
                    "status": "pending"
                },
                {
                    "job_id": 14,
                    "op_id": 5,
                    "machine": 8,
                    "processing_time": 11.694769316811211,
                    "setup_time": 2.1045241962485886,
                    "status": "pending"
                },
                {
                    "job_id": 14,
                    "op_id": 6,
                    "machine": 2,
                    "processing_time": 11.253075953823751,
                    "setup_time": 1.320068127097286,
                    "status": "pending"
                },
                {
                    "job_id": 14,
                    "op_id": 7,
                    "machine": 6,
                    "processing_time": 2.088948911272475,
                    "setup_time": 0.2432176432215366,
                    "status": "pending"
                }
            ],
            "arrival_time": 25,
            "completed_operations": 0,
            "priority": 1,
            "machine_seq": [
                3,
                5,
                0,
                4,
                1,
                8,
                2,
                6
            ],
            "current_operation": 0
        },
        {
            "job_id": 15,
            "operations": [
                {
                    "job_id": 15,
                    "op_id": 0,
                    "machine": 6,
                    "processing_time": 5.638521356186855,
                    "setup_time": 0.0,
                    "status": "pending"
                },
                {
                    "job_id": 15,
                    "op_id": 1,
                    "machine": 2,
                    "processing_time": 16.678623526702612,
                    "setup_time": 2.287097524883953,
                    "status": "pending"
                },
                {
                    "job_id": 15,
                    "op_id": 2,
                    "machine": 8,
                    "processing_time": 12.485518477746751,
                    "setup_time": 1.7030510341513352,
                    "status": "pending"
                },
                {
                    "job_id": 15,
                    "op_id": 3,
                    "machine": 1,
                    "processing_time": 15.742625493516417,
                    "setup_time": 2.7151360606592267,
                    "status": "pending"
                },
                {
                    "job_id": 15,
                    "op_id": 4,
                    "machine": 7,
                    "processing_time": 9.458899135035544,
                    "setup_time": 1.5739582010421962,
                    "status": "pending"
                },
                {
                    "job_id": 15,
                    "op_id": 5,
                    "machine": 1,
                    "processing_time": 8.00862362346027,
                    "setup_time": 2.946428968158413,
                    "status": "pending"
                }
            ],
            "arrival_time": 39,
            "completed_operations": 0,
            "priority": 1,
            "machine_seq": [
                6,
                2,
                8,
                1,
                7,
                1
            ],
            "current_operation": 0
        },
        {
            "job_id": 16,
            "operations": [
                {
                    "job_id": 16,
                    "op_id": 0,
                    "machine": 3,
                    "processing_time": 11.256671370656168,
                    "setup_time": 0.0,
                    "status": "pending"
                },
                {
                    "job_id": 16,
                    "op_id": 1,
                    "machine": 5,
                    "processing_time": 6.798574536259212,
                    "setup_time": 0.962083861353664,
                    "status": "pending"
                },
                {
                    "job_id": 16,
                    "op_id": 2,
                    "machine": 8,
                    "processing_time": 6.6874568164498225,
                    "setup_time": 1.1941414517626003,
                    "status": "pending"
                },
                {
                    "job_id": 16,
                    "op_id": 3,
                    "machine": 2,
                    "processing_time": 16.52533668680109,
                    "setup_time": 2.7855628044117244,
                    "status": "pending"
                },
                {
                    "job_id": 16,
                    "op_id": 4,
                    "machine": 6,
                    "processing_time": 9.533120627490096,
                    "setup_time": 2.484921235101762,
                    "status": "pending"
                }
            ],
            "arrival_time": 21,
            "completed_operations": 0,
            "priority": 3,
            "machine_seq": [
                3,
                5,
                8,
                2,
                6
            ],
            "current_operation": 0
        },
        {
            "job_id": 17,
            "operations": [
                {
                    "job_id": 17,
                    "op_id": 0,
                    "machine": 5,
                    "processing_time": 3.9352373200319644,
                    "setup_time": 0.0,
                    "status": "pending"
                },
                {
                    "job_id": 17,
                    "op_id": 1,
                    "machine": 3,
                    "processing_time": 10.819208422269961,
                    "setup_time": 1.6985573802946794,
                    "status": "pending"
                },
                {
                    "job_id": 17,
                    "op_id": 2,
                    "machine": 1,
                    "processing_time": 9.150016873468775,
                    "setup_time": 0.03514326867020556,
                    "status": "pending"
                },
                {
                    "job_id": 17,
                    "op_id": 3,
                    "machine": 1,
                    "processing_time": 10.18874319216477,
                    "setup_time": 0.3639054485955643,
                    "status": "pending"
                },
                {
                    "job_id": 17,
                    "op_id": 4,
                    "machine": 4,
                    "processing_time": 16.417470175206283,
                    "setup_time": 1.89689190051456,
                    "status": "pending"
                },
                {
                    "job_id": 17,
                    "op_id": 5,
                    "machine": 2,
                    "processing_time": 3.850759981245276,
                    "setup_time": 2.944291672474733,
                    "status": "pending"
                },
                {
                    "job_id": 17,
                    "op_id": 6,
                    "machine": 6,
                    "processing_time": 15.594795514240932,
                    "setup_time": 0.4011106912966791,
                    "status": "pending"
                }
            ],
            "arrival_time": 38,
            "completed_operations": 0,
            "priority": 1,
            "machine_seq": [
                5,
                3,
                1,
                1,
                4,
                2,
                6
            ],
            "current_operation": 0
        },
        {
            "job_id": 18,
            "operations": [
                {
                    "job_id": 18,
                    "op_id": 0,
                    "machine": 5,
                    "processing_time": 16.335425262329004,
                    "setup_time": 0.0,
                    "status": "pending"
                },
                {
                    "job_id": 18,
                    "op_id": 1,
                    "machine": 1,
                    "processing_time": 14.004878085234616,
                    "setup_time": 1.256484816171162,
                    "status": "pending"
                },
                {
                    "job_id": 18,
                    "op_id": 2,
                    "machine": 4,
                    "processing_time": 10.073816727262786,
                    "setup_time": 0.31745236487038886,
                    "status": "pending"
                },
                {
                    "job_id": 18,
                    "op_id": 3,
                    "machine": 5,
                    "processing_time": 9.41897232456591,
                    "setup_time": 0.7822256514007486,
                    "status": "pending"
                },
                {
                    "job_id": 18,
                    "op_id": 4,
                    "machine": 9,
                    "processing_time": 15.054370597933175,
                    "setup_time": 0.2621200222696397,
                    "status": "pending"
                },
                {
                    "job_id": 18,
                    "op_id": 5,
                    "machine": 6,
                    "processing_time": 7.256897270360195,
                    "setup_time": 1.7398796438472381,
                    "status": "pending"
                }
            ],
            "arrival_time": 8,
            "completed_operations": 0,
            "priority": 5,
            "machine_seq": [
                5,
                1,
                4,
                5,
                9,
                6
            ],
            "current_operation": 0
        },
        {
            "job_id": 19,
            "operations": [
                {
                    "job_id": 19,
                    "op_id": 0,
                    "machine": 9,
                    "processing_time": 10.171731330528333,
                    "setup_time": 0.0,
                    "status": "pending"
                },
                {
                    "job_id": 19,
                    "op_id": 1,
                    "machine": 1,
                    "processing_time": 14.068624839055147,
                    "setup_time": 2.960971299589969,
                    "status": "pending"
                },
                {
                    "job_id": 19,
                    "op_id": 2,
                    "machine": 5,
                    "processing_time": 15.823373700252976,
                    "setup_time": 0.606221617386582,
                    "status": "pending"
                },
                {
                    "job_id": 19,
                    "op_id": 3,
                    "machine": 2,
                    "processing_time": 9.081338380559448,
                    "setup_time": 2.0024553468793638,
                    "status": "pending"
                }
            ],
            "arrival_time": 5,
            "completed_operations": 0,
            "priority": 3,
            "machine_seq": [
                9,
                1,
                5,
                2
            ],
            "current_operation": 0
        },
        {
            "job_id": 20,
            "operations": [
                {
                    "job_id": 20,
                    "op_id": 0,
                    "machine": 0,
                    "processing_time": 8.830909837095863,
                    "setup_time": 0.0,
                    "status": "pending"
                },
                {
                    "job_id": 20,
                    "op_id": 1,
                    "machine": 6,
                    "processing_time": 7.316031812522964,
                    "setup_time": 1.0258035434307775,
                    "status": "pending"
                },
                {
                    "job_id": 20,
                    "op_id": 2,
                    "machine": 7,
                    "processing_time": 14.070508581394193,
                    "setup_time": 2.712748610472224,
                    "status": "pending"
                },
                {
                    "job_id": 20,
                    "op_id": 3,
                    "machine": 1,
                    "processing_time": 19.49216269514829,
                    "setup_time": 2.5782324812574284,
                    "status": "pending"
                },
                {
                    "job_id": 20,
                    "op_id": 4,
                    "machine": 7,
                    "processing_time": 12.806926196520912,
                    "setup_time": 2.090736338472274,
                    "status": "pending"
                },
                {
                    "job_id": 20,
                    "op_id": 5,
                    "machine": 3,
                    "processing_time": 14.313628794411713,
                    "setup_time": 1.3205529302806356,
                    "status": "pending"
                },
                {
                    "job_id": 20,
                    "op_id": 6,
                    "machine": 5,
                    "processing_time": 10.492498817877047,
                    "setup_time": 2.710942333991158,
                    "status": "pending"
                },
                {
                    "job_id": 20,
                    "op_id": 7,
                    "machine": 7,
                    "processing_time": 13.39045515985621,
                    "setup_time": 2.4728253096061885,
                    "status": "pending"
                }
            ],
            "arrival_time": 11,
            "completed_operations": 0,
            "priority": 2,
            "machine_seq": [
                0,
                6,
                7,
                1,
                7,
                3,
                5,
                7
            ],
            "current_operation": 0
        },
        {
            "job_id": 21,
            "operations": [
                {
                    "job_id": 21,
                    "op_id": 0,
                    "machine": 1,
                    "processing_time": 3.8048049758890183,
                    "setup_time": 0.0,
                    "status": "pending"
                },
                {
                    "job_id": 21,
                    "op_id": 1,
                    "machine": 4,
                    "processing_time": 8.82140312566381,
                    "setup_time": 0.47443119452264504,
                    "status": "pending"
                },
                {
                    "job_id": 21,
                    "op_id": 2,
                    "machine": 5,
                    "processing_time": 6.92370723571041,
                    "setup_time": 0.742074460877122,
                    "status": "pending"
                },
                {
                    "job_id": 21,
                    "op_id": 3,
                    "machine": 2,
                    "processing_time": 7.906506028306899,
                    "setup_time": 0.9212756289532118,
                    "status": "pending"
                },
                {
                    "job_id": 21,
                    "op_id": 4,
                    "machine": 3,
                    "processing_time": 7.720523280541867,
                    "setup_time": 0.38637760587656544,
                    "status": "pending"
                }
            ],
            "arrival_time": 50,
            "completed_operations": 0,
            "priority": 2,
            "machine_seq": [
                1,
                4,
                5,
                2,
                3
            ],
            "current_operation": 0
        },
        {
            "job_id": 22,
            "operations": [
                {
                    "job_id": 22,
                    "op_id": 0,
                    "machine": 7,
                    "processing_time": 6.815060285430186,
                    "setup_time": 0.0,
                    "status": "pending"
                },
                {
                    "job_id": 22,
                    "op_id": 1,
                    "machine": 5,
                    "processing_time": 17.048441980178353,
                    "setup_time": 2.8745644605761447,
                    "status": "pending"
                },
                {
                    "job_id": 22,
                    "op_id": 2,
                    "machine": 1,
                    "processing_time": 6.660745971442671,
                    "setup_time": 0.5934607249348448,
                    "status": "pending"
                },
                {
                    "job_id": 22,
                    "op_id": 3,
                    "machine": 8,
                    "processing_time": 3.813991173695748,
                    "setup_time": 0.4610332804490348,
                    "status": "pending"
                }
            ],
            "arrival_time": 12,
            "completed_operations": 0,
            "priority": 2,
            "machine_seq": [
                7,
                5,
                1,
                8
            ],
            "current_operation": 0
        },
        {
            "job_id": 23,
            "operations": [
                {
                    "job_id": 23,
                    "op_id": 0,
                    "machine": 3,
                    "processing_time": 11.893717141708278,
                    "setup_time": 0.0,
                    "status": "pending"
                },
                {
                    "job_id": 23,
                    "op_id": 1,
                    "machine": 7,
                    "processing_time": 11.129239527099985,
                    "setup_time": 2.809011792246192,
                    "status": "pending"
                },
                {
                    "job_id": 23,
                    "op_id": 2,
                    "machine": 1,
                    "processing_time": 8.945452208150158,
                    "setup_time": 2.0830304617376014,
                    "status": "pending"
                },
                {
                    "job_id": 23,
                    "op_id": 3,
                    "machine": 9,
                    "processing_time": 9.066972522197862,
                    "setup_time": 1.1984054858949895,
                    "status": "pending"
                },
                {
                    "job_id": 23,
                    "op_id": 4,
                    "machine": 6,
                    "processing_time": 18.894137002863484,
                    "setup_time": 1.5961208917791474,
                    "status": "pending"
                }
            ],
            "arrival_time": 24,
            "completed_operations": 0,
            "priority": 4,
            "machine_seq": [
                3,
                7,
                1,
                9,
                6
            ],
            "current_operation": 0
        },
        {
            "job_id": 24,
            "operations": [
                {
                    "job_id": 24,
                    "op_id": 0,
                    "machine": 7,
                    "processing_time": 9.37870332541158,
                    "setup_time": 0.0,
                    "status": "pending"
                },
                {
                    "job_id": 24,
                    "op_id": 1,
                    "machine": 3,
                    "processing_time": 11.342158775386896,
                    "setup_time": 2.3685063630627976,
                    "status": "pending"
                },
                {
                    "job_id": 24,
                    "op_id": 2,
                    "machine": 1,
                    "processing_time": 12.106990456830268,
                    "setup_time": 2.771803532292604,
                    "status": "pending"
                },
                {
                    "job_id": 24,
                    "op_id": 3,
                    "machine": 0,
                    "processing_time": 8.338738385697617,
                    "setup_time": 2.829412767047054,
                    "status": "pending"
                }
            ],
            "arrival_time": 5,
            "completed_operations": 0,
            "priority": 4,
            "machine_seq": [
                7,
                3,
                1,
                0
            ],
            "current_operation": 0
        },
        {
            "job_id": 25,
            "operations": [
                {
                    "job_id": 25,
                    "op_id": 0,
                    "machine": 1,
                    "processing_time": 14.305608760349124,
                    "setup_time": 0.0,
                    "status": "pending"
                },
                {
                    "job_id": 25,
                    "op_id": 1,
                    "machine": 5,
                    "processing_time": 13.23855713951972,
                    "setup_time": 1.0985782211106034,
                    "status": "pending"
                },
                {
                    "job_id": 25,
                    "op_id": 2,
                    "machine": 0,
                    "processing_time": 9.432594645305382,
                    "setup_time": 1.2064192960584594,
                    "status": "pending"
                },
                {
                    "job_id": 25,
                    "op_id": 3,
                    "machine": 3,
                    "processing_time": 12.994196581120413,
                    "setup_time": 1.7394063677790386,
                    "status": "pending"
                },
                {
                    "job_id": 25,
                    "op_id": 4,
                    "machine": 4,
                    "processing_time": 16.781142290345965,
                    "setup_time": 0.28604052143634917,
                    "status": "pending"
                },
                {
                    "job_id": 25,
                    "op_id": 5,
                    "machine": 2,
                    "processing_time": 11.421622292942757,
                    "setup_time": 1.323614517736679,
                    "status": "pending"
                },
                {
                    "job_id": 25,
                    "op_id": 6,
                    "machine": 9,
                    "processing_time": 4.574937325632972,
                    "setup_time": 0.911334026852811,
                    "status": "pending"
                }
            ],
            "arrival_time": 30,
            "completed_operations": 0,
            "priority": 4,
            "machine_seq": [
                1,
                5,
                0,
                3,
                4,
                2,
                9
            ],
            "current_operation": 0
        },
        {
            "job_id": 26,
            "operations": [
                {
                    "job_id": 26,
                    "op_id": 0,
                    "machine": 1,
                    "processing_time": 5.420657179733102,
                    "setup_time": 0.0,
                    "status": "pending"
                },
                {
                    "job_id": 26,
                    "op_id": 1,
                    "machine": 8,
                    "processing_time": 15.795504884939131,
                    "setup_time": 2.962291497984978,
                    "status": "pending"
                },
                {
                    "job_id": 26,
                    "op_id": 2,
                    "machine": 2,
                    "processing_time": 8.619881438174502,
                    "setup_time": 1.4479962685260395,
                    "status": "pending"
                },
                {
                    "job_id": 26,
                    "op_id": 3,
                    "machine": 5,
                    "processing_time": 16.60299232313005,
                    "setup_time": 0.9092023890117862,
                    "status": "pending"
                },
                {
                    "job_id": 26,
                    "op_id": 4,
                    "machine": 9,
                    "processing_time": 16.562400554515666,
                    "setup_time": 2.8621817977242086,
                    "status": "pending"
                },
                {
                    "job_id": 26,
                    "op_id": 5,
                    "machine": 7,
                    "processing_time": 5.816941994006303,
                    "setup_time": 2.6208968830349813,
                    "status": "pending"
                },
                {
                    "job_id": 26,
                    "op_id": 6,
                    "machine": 1,
                    "processing_time": 2.773653321003439,
                    "setup_time": 1.117354638397406,
                    "status": "pending"
                }
            ],
            "arrival_time": 20,
            "completed_operations": 0,
            "priority": 1,
            "machine_seq": [
                1,
                8,
                2,
                5,
                9,
                7,
                1
            ],
            "current_operation": 0
        },
        {
            "job_id": 27,
            "operations": [
                {
                    "job_id": 27,
                    "op_id": 0,
                    "machine": 6,
                    "processing_time": 11.166912435457473,
                    "setup_time": 0.0,
                    "status": "pending"
                },
                {
                    "job_id": 27,
                    "op_id": 1,
                    "machine": 4,
                    "processing_time": 5.418525794524349,
                    "setup_time": 1.6416539253658144,
                    "status": "pending"
                },
                {
                    "job_id": 27,
                    "op_id": 2,
                    "machine": 5,
                    "processing_time": 10.180909944560208,
                    "setup_time": 1.1577896909260972,
                    "status": "pending"
                },
                {
                    "job_id": 27,
                    "op_id": 3,
                    "machine": 7,
                    "processing_time": 6.7193220053187375,
                    "setup_time": 0.4261865362246018,
                    "status": "pending"
                },
                {
                    "job_id": 27,
                    "op_id": 4,
                    "machine": 2,
                    "processing_time": 16.17171025756947,
                    "setup_time": 1.0668325422898084,
                    "status": "pending"
                },
                {
                    "job_id": 27,
                    "op_id": 5,
                    "machine": 1,
                    "processing_time": 14.265724376351907,
                    "setup_time": 2.789243754634679,
                    "status": "pending"
                },
                {
                    "job_id": 27,
                    "op_id": 6,
                    "machine": 4,
                    "processing_time": 10.053956511662903,
                    "setup_time": 0.4044503396830291,
                    "status": "pending"
                }
            ],
            "arrival_time": 35,
            "completed_operations": 0,
            "priority": 3,
            "machine_seq": [
                6,
                4,
                5,
                7,
                2,
                1,
                4
            ],
            "current_operation": 0
        }
    ],
    "machines": [
        {
            "machine_id": 0,
            "status": "available",
            "current_job": null,
            "next_available_time": 0,
            "type": "general"
        },
        {
            "machine_id": 1,
            "status": "available",
            "current_job": null,
            "next_available_time": 0,
            "type": "special"
        },
        {
            "machine_id": 2,
            "status": "available",
            "current_job": null,
            "next_available_time": 0,
            "type": "special"
        },
        {
            "machine_id": 3,
            "status": "available",
            "current_job": null,
            "next_available_time": 0,
            "type": "general"
        },
        {
            "machine_id": 4,
            "status": "available",
            "current_job": null,
            "next_available_time": 0,
            "type": "special"
        },
        {
            "machine_id": 5,
            "status": "available",
            "current_job": null,
            "next_available_time": 0,
            "type": "special"
        },
        {
            "machine_id": 6,
            "status": "available",
            "current_job": null,
            "next_available_time": 0,
            "type": "special"
        },
        {
            "machine_id": 7,
            "status": "available",
            "current_job": null,
            "next_available_time": 0,
            "type": "general"
        },
        {
            "machine_id": 8,
            "status": "available",
            "current_job": null,
            "next_available_time": 0,
            "type": "special"
        },
        {
            "machine_id": 9,
            "status": "available",
            "current_job": null,
            "next_available_time": 0,
            "type": "general"
        }
    ],
    "resources": {
        "resource_capacity": 6,
        "machines": [
            {
                "machine_id": 8,
                "status": "available",
                "current_job": null,
                "next_available_time": 0,
                "type": "special"
            },
            {
                "machine_id": 6,
                "status": "available",
                "current_job": null,
                "next_available_time": 0,
                "type": "special"
            },
            {
                "machine_id": 7,
                "status": "available",
                "current_job": null,
                "next_available_time": 0,
                "type": "general"
            },
            {
                "machine_id": 0,
                "status": "available",
                "current_job": null,
                "next_available_time": 0,
                "type": "general"
            },
            {
                "machine_id": 4,
                "status": "available",
                "current_job": null,
                "next_available_time": 0,
                "type": "special"
            },
            {
                "machine_id": 1,
                "status": "available",
                "current_job": null,
                "next_available_time": 0,
                "type": "special"
            }
        ]
    }
}