{
    "jobs": [
        {
            "job_id": 0,
            "operations": [
                {
                    "job_id": 0,
                    "op_id": 0,
                    "machine": 5,
                    "processing_time": 5.396792923590976,
                    "setup_time": 0.0,
                    "status": "pending"
                },
                {
                    "job_id": 0,
                    "op_id": 1,
                    "machine": 7,
                    "processing_time": 2.89935703544982,
                    "setup_time": 0.2770703562769369,
                    "status": "pending"
                },
                {
                    "job_id": 0,
                    "op_id": 2,
                    "machine": 3,
                    "processing_time": 12.987209268284023,
                    "setup_time": 0.4823303925591965,
                    "status": "pending"
                }
            ],
            "arrival_time": 3,
            "completed_operations": 0,
            "priority": 4,
            "machine_seq": [
                5,
                7,
                3
            ],
            "current_operation": 0
        },
        {
            "job_id": 1,
            "operations": [
                {
                    "job_id": 1,
                    "op_id": 0,
                    "machine": 9,
                    "processing_time": 12.808904205080257,
                    "setup_time": 0.0,
                    "status": "pending"
                },
                {
                    "job_id": 1,
                    "op_id": 1,
                    "machine": 4,
                    "processing_time": 5.73108523304707,
                    "setup_time": 0.5755519466964373,
                    "status": "pending"
                },
                {
                    "job_id": 1,
                    "op_id": 2,
                    "machine": 9,
                    "processing_time": 17.921163520552785,
                    "setup_time": 2.5891347284198694,
                    "status": "pending"
                },
                {
                    "job_id": 1,
                    "op_id": 3,
                    "machine": 5,
                    "processing_time": 11.48559504655771,
                    "setup_time": 0.7472802404941351,
                    "status": "pending"
                }
            ],
            "arrival_time": 27,
            "completed_operations": 0,
            "priority": 3,
            "machine_seq": [
                9,
                4,
                9,
                5
            ],
            "current_operation": 0
        },
        {
            "job_id": 2,
            "operations": [
                {
                    "job_id": 2,
                    "op_id": 0,
                    "machine": 8,
                    "processing_time": 13.740280416074746,
                    "setup_time": 0.0,
                    "status": "pending"
                },
                {
                    "job_id": 2,
                    "op_id": 1,
                    "machine": 3,
                    "processing_time": 12.274140671168373,
                    "setup_time": 1.1281559011052984,
                    "status": "pending"
                },
                {
                    "job_id": 2,
                    "op_id": 2,
                    "machine": 6,
                    "processing_time": 10.2079101789996,
                    "setup_time": 2.3174106103702736,
                    "status": "pending"
                }
            ],
            "arrival_time": 36,
            "completed_operations": 0,
            "priority": 5,
            "machine_seq": [
                8,
                3,
                6
            ],
            "current_operation": 0
        },
        {
            "job_id": 3,
            "operations": [
                {
                    "job_id": 3,
                    "op_id": 0,
                    "machine": 7,
                    "processing_time": 12.361285720018742,
                    "setup_time": 0.0,
                    "status": "pending"
                },
                {
                    "job_id": 3,
                    "op_id": 1,
                    "machine": 1,
                    "processing_time": 7.668266413336411,
                    "setup_time": 0.5786139173715218,
                    "status": "pending"
                },
                {
                    "job_id": 3,
                    "op_id": 2,
                    "machine": 3,
                    "processing_time": 7.78142239940191,
                    "setup_time": 2.1370420782228865,
                    "status": "pending"
                },
                {
                    "job_id": 3,
                    "op_id": 3,
                    "machine": 9,
                    "processing_time": 11.875060491310403,
                    "setup_time": 2.514358814945032,
                    "status": "pending"
                },
                {
                    "job_id": 3,
                    "op_id": 4,
                    "machine": 5,
                    "processing_time": 12.701660368077178,
                    "setup_time": 0.3715592531247365,
                    "status": "pending"
                }
            ],
            "arrival_time": 29,
            "completed_operations": 0,
            "priority": 3,
            "machine_seq": [
                7,
                1,
                3,
                9,
                5
            ],
            "current_operation": 0
        },
        {
            "job_id": 4,
            "operations": [
                {
                    "job_id": 4,
                    "op_id": 0,
                    "machine": 1,
                    "processing_time": 16.72715378273204,
                    "setup_time": 0.0,
                    "status": "pending"
                },
                {
                    "job_id": 4,
                    "op_id": 1,
                    "machine": 4,
                    "processing_time": 6.797849762867095,
                    "setup_time": 1.2607543676764472,
                    "status": "pending"
                },
                {
                    "job_id": 4,
                    "op_id": 2,
                    "machine": 4,
                    "processing_time": 15.337777122820032,
                    "setup_time": 2.5839936523767815,
                    "status": "pending"
                },
                {
                    "job_id": 4,
                    "op_id": 3,
                    "machine": 2,
                    "processing_time": 12.469167429975695,
                    "setup_time": 1.3217759084219516,
                    "status": "pending"
                },
                {
                    "job_id": 4,
                    "op_id": 4,
                    "machine": 7,
                    "processing_time": 4.65619213364169,
                    "setup_time": 0.15320686816719542,
                    "status": "pending"
                },
                {
                    "job_id": 4,
                    "op_id": 5,
                    "machine": 6,
                    "processing_time": 11.363941474405859,
                    "setup_time": 2.175143808486741,
                    "status": "pending"
                },
                {
                    "job_id": 4,
                    "op_id": 6,
                    "machine": 8,
                    "processing_time": 15.449419096538467,
                    "setup_time": 0.21140531981260646,
                    "status": "pending"
                },
                {
                    "job_id": 4,
                    "op_id": 7,
                    "machine": 8,
                    "processing_time": 13.522720773952344,
                    "setup_time": 0.0012039986392429203,
                    "status": "pending"
                }
            ],
            "arrival_time": 50,
            "completed_operations": 0,
            "priority": 1,
            "machine_seq": [
                1,
                4,
                4,
                2,
                7,
                6,
                8,
                8
            ],
            "current_operation": 0
        },
        {
            "job_id": 5,
            "operations": [
                {
                    "job_id": 5,
                    "op_id": 0,
                    "machine": 4,
                    "processing_time": 13.23093201894116,
                    "setup_time": 0.0,
                    "status": "pending"
                },
                {
                    "job_id": 5,
                    "op_id": 1,
                    "machine": 7,
                    "processing_time": 9.065161461984152,
                    "setup_time": 1.31147307820607,
                    "status": "pending"
                },
                {
                    "job_id": 5,
                    "op_id": 2,
                    "machine": 1,
                    "processing_time": 12.829876901820764,
                    "setup_time": 0.9083337137760598,
                    "status": "pending"
                },
                {
                    "job_id": 5,
                    "op_id": 3,
                    "machine": 3,
                    "processing_time": 12.409937558568505,
                    "setup_time": 0.2507109566231438,
                    "status": "pending"
                }
            ],
            "arrival_time": 42,
            "completed_operations": 0,
            "priority": 2,
            "machine_seq": [
                4,
                7,
                1,
                3
            ],
            "current_operation": 0
        },
        {
            "job_id": 6,
            "operations": [
                {
                    "job_id": 6,
                    "op_id": 0,
                    "machine": 2,
                    "processing_time": 11.131841793405515,
                    "setup_time": 0.0,
                    "status": "pending"
                },
                {
                    "job_id": 6,
                    "op_id": 1,
                    "machine": 5,
                    "processing_time": 13.577105806372217,
                    "setup_time": 0.8871233692058953,
                    "status": "pending"
                },
                {
                    "job_id": 6,
                    "op_id": 2,
                    "machine": 1,
                    "processing_time": 11.758696496293831,
                    "setup_time": 1.687749523767454,
                    "status": "pending"
                },
                {
                    "job_id": 6,
                    "op_id": 3,
                    "machine": 1,
                    "processing_time": 7.579277578002866,
                    "setup_time": 2.5477579004013604,
                    "status": "pending"
                },
                {
                    "job_id": 6,
                    "op_id": 4,
                    "machine": 6,
                    "processing_time": 14.051129792101372,
                    "setup_time": 2.6316153364084984,
                    "status": "pending"
                },
                {
                    "job_id": 6,
                    "op_id": 5,
                    "machine": 2,
                    "processing_time": 9.94606229130374,
                    "setup_time": 1.5829724290729907,
                    "status": "pending"
                },
                {
                    "job_id": 6,
                    "op_id": 6,
                    "machine": 5,
                    "processing_time": 7.817252244041809,
                    "setup_time": 2.8429791192102236,
                    "status": "pending"
                },
                {
                    "job_id": 6,
                    "op_id": 7,
                    "machine": 6,
                    "processing_time": 11.451902665738144,
                    "setup_time": 2.6843505530643954,
                    "status": "pending"
                }
            ],
            "arrival_time": 11,
            "completed_operations": 0,
            "priority": 4,
            "machine_seq": [
                2,
                5,
                1,
                1,
                6,
                2,
                5,
                6
            ],
            "current_operation": 0
        },
        {
            "job_id": 7,
            "operations": [
                {
                    "job_id": 7,
                    "op_id": 0,
                    "machine": 2,
                    "processing_time": 13.733915492937136,
                    "setup_time": 0.0,
                    "status": "pending"
                },
                {
                    "job_id": 7,
                    "op_id": 1,
                    "machine": 0,
                    "processing_time": 5.408637622177801,
                    "setup_time": 0.9244189006224413,
                    "status": "pending"
                },
                {
                    "job_id": 7,
                    "op_id": 2,
                    "machine": 5,
                    "processing_time": 8.563803395580436,
                    "setup_time": 2.0093958425986695,
                    "status": "pending"
                },
                {
                    "job_id": 7,
                    "op_id": 3,
                    "machine": 1,
                    "processing_time": 12.803953548799253,
                    "setup_time": 0.4658032769151206,
                    "status": "pending"
                },
                {
                    "job_id": 7,
                    "op_id": 4,
                    "machine": 9,
                    "processing_time": 10.16010464519883,
                    "setup_time": 2.9222219812167465,
                    "status": "pending"
                },
                {
                    "job_id": 7,
                    "op_id": 5,
                    "machine": 9,
                    "processing_time": 15.29129923619503,
                    "setup_time": 2.5488740559758583,
                    "status": "pending"
                },
                {
                    "job_id": 7,
                    "op_id": 6,
                    "machine": 3,
                    "processing_time": 12.843308142948342,
                    "setup_time": 0.9424760318762104,
                    "status": "pending"
                },
                {
                    "job_id": 7,
                    "op_id": 7,
                    "machine": 4,
                    "processing_time": 12.86902036346242,
                    "setup_time": 1.15577932948548,
                    "status": "pending"
                }
            ],
            "arrival_time": 34,
            "completed_operations": 0,
            "priority": 1,
            "machine_seq": [
                2,
                0,
                5,
                1,
                9,
                9,
                3,
                4
            ],
            "current_operation": 0
        },
        {
            "job_id": 8,
            "operations": [
                {
                    "job_id": 8,
                    "op_id": 0,
                    "machine": 8,
                    "processing_time": 7.096019476432015,
                    "setup_time": 0.0,
                    "status": "pending"
                },
                {
                    "job_id": 8,
                    "op_id": 1,
                    "machine": 0,
                    "processing_time": 10.186112608013282,
                    "setup_time": 0.0191387858105172,
                    "status": "pending"
                },
                {
                    "job_id": 8,
                    "op_id": 2,
                    "machine": 4,
                    "processing_time": 9.042087531245855,
                    "setup_time": 0.3667358929020015,
                    "status": "pending"
                },
                {
                    "job_id": 8,
                    "op_id": 3,
                    "machine": 7,
                    "processing_time": 10.293114771772164,
                    "setup_time": 0.8618689955046845,
                    "status": "pending"
                },
                {
                    "job_id": 8,
                    "op_id": 4,
                    "machine": 7,
                    "processing_time": 4.693082532987795,
                    "setup_time": 2.2954752663671147,
                    "status": "pending"
                },
                {
                    "job_id": 8,
                    "op_id": 5,
                    "machine": 5,
                    "processing_time": 17.164709258159405,
                    "setup_time": 1.3662051187917417,
                    "status": "pending"
                },
                {
                    "job_id": 8,
                    "op_id": 6,
                    "machine": 8,
                    "processing_time": 10.51438875359044,
                    "setup_time": 0.6021117167543737,
                    "status": "pending"
                }
            ],
            "arrival_time": 25,
            "completed_operations": 0,
            "priority": 3,
            "machine_seq": [
                8,
                0,
                4,
                7,
                7,
                5,
                8
            ],
            "current_operation": 0
        },
        {
            "job_id": 9,
            "operations": [
                {
                    "job_id": 9,
                    "op_id": 0,
                    "machine": 1,
                    "processing_time": 13.553510992844894,
                    "setup_time": 0.0,
                    "status": "pending"
                },
                {
                    "job_id": 9,
                    "op_id": 1,
                    "machine": 5,
                    "processing_time": 11.072192739051028,
                    "setup_time": 1.6754229693422698,
                    "status": "pending"
                },
                {
                    "job_id": 9,
                    "op_id": 2,
                    "machine": 6,
                    "processing_time": 15.413096295448998,
                    "setup_time": 2.6622709278486067,
                    "status": "pending"
                },
                {
                    "job_id": 9,
                    "op_id": 3,
                    "machine": 2,
                    "processing_time": 11.916400099248452,
                    "setup_time": 1.6013457302846785,
                    "status": "pending"
                },
                {
                    "job_id": 9,
                    "op_id": 4,
                    "machine": 1,
                    "processing_time": 11.37907295177882,
                    "setup_time": 0.2785782631036381,
                    "status": "pending"
                },
                {
                    "job_id": 9,
                    "op_id": 5,
                    "machine": 4,
                    "processing_time": 8.451307615597527,
                    "setup_time": 0.19316859507941697,
                    "status": "pending"
                },
                {
                    "job_id": 9,
                    "op_id": 6,
                    "machine": 5,
                    "processing_time": 5.100919909413524,
                    "setup_time": 2.1354381994353298,
                    "status": "pending"
                }
            ],
            "arrival_time": 19,
            "completed_operations": 0,
            "priority": 5,
            "machine_seq": [
                1,
                5,
                6,
                2,
                1,
                4,
                5
            ],
            "current_operation": 0
        },
        {
            "job_id": 10,
            "operations": [
                {
                    "job_id": 10,
                    "op_id": 0,
                    "machine": 9,
                    "processing_time": 9.233370378003105,
                    "setup_time": 0.0,
                    "status": "pending"
                },
                {
                    "job_id": 10,
                    "op_id": 1,
                    "machine": 4,
                    "processing_time": 12.344479310882111,
                    "setup_time": 1.0390775856035428,
                    "status": "pending"
                },
                {
                    "job_id": 10,
                    "op_id": 2,
                    "machine": 7,
                    "processing_time": 9.899896204785794,
                    "setup_time": 0.14858809226628755,
                    "status": "pending"
                },
                {
                    "job_id": 10,
                    "op_id": 3,
                    "machine": 9,
                    "processing_time": 4.131966459962716,
                    "setup_time": 0.8481184768870212,
                    "status": "pending"
                },
                {
                    "job_id": 10,
                    "op_id": 4,
                    "machine": 6,
                    "processing_time": 5.817246977966093,
                    "setup_time": 1.0412931755245824,
                    "status": "pending"
                },
                {
                    "job_id": 10,
                    "op_id": 5,
                    "machine": 4,
                    "processing_time": 13.941744442102367,
                    "setup_time": 2.162332979417677,
                    "status": "pending"
                }
            ],
            "arrival_time": 37,
            "completed_operations": 0,
            "priority": 2,
            "machine_seq": [
                9,
                4,
                7,
                9,
                6,
                4
            ],
            "current_operation": 0
        },
        {
            "job_id": 11,
            "operations": [
                {
                    "job_id": 11,
                    "op_id": 0,
                    "machine": 8,
                    "processing_time": 13.151777279637344,
                    "setup_time": 0.0,
                    "status": "pending"
                },
                {
                    "job_id": 11,
                    "op_id": 1,
                    "machine": 8,
                    "processing_time": 11.078030410112325,
                    "setup_time": 0.3038128534345156,
                    "status": "pending"
                },
                {
                    "job_id": 11,
                    "op_id": 2,
                    "machine": 7,
                    "processing_time": 12.50236166952305,
                    "setup_time": 0.10551873261663758,
                    "status": "pending"
                },
                {
                    "job_id": 11,
                    "op_id": 3,
                    "machine": 1,
                    "processing_time": 4.257631961870832,
                    "setup_time": 0.1762714158806611,
                    "status": "pending"
                },
                {
                    "job_id": 11,
                    "op_id": 4,
                    "machine": 0,
                    "processing_time": 8.636838525940949,
                    "setup_time": 1.3873397800016578,
                    "status": "pending"
                }
            ],
            "arrival_time": 32,
            "completed_operations": 0,
            "priority": 2,
            "machine_seq": [
                8,
                8,
                7,
                1,
                0
            ],
            "current_operation": 0
        },
        {
            "job_id": 12,
            "operations": [
                {
                    "job_id": 12,
                    "op_id": 0,
                    "machine": 9,
                    "processing_time": 7.9350347267350525,
                    "setup_time": 0.0,
                    "status": "pending"
                },
                {
                    "job_id": 12,
                    "op_id": 1,
                    "machine": 3,
                    "processing_time": 8.866248259143541,
                    "setup_time": 0.34538153288461604,
                    "status": "pending"
                },
                {
                    "job_id": 12,
                    "op_id": 2,
                    "machine": 9,
                    "processing_time": 4.590169439067667,
                    "setup_time": 0.9802464207049902,
                    "status": "pending"
                },
                {
                    "job_id": 12,
                    "op_id": 3,
                    "machine": 4,
                    "processing_time": 10.176405452180207,
                    "setup_time": 1.8716438587970807,
                    "status": "pending"
                },
                {
                    "job_id": 12,
                    "op_id": 4,
                    "machine": 9,
                    "processing_time": 14.757614122350445,
                    "setup_time": 2.575571896316977,
                    "status": "pending"
                },
                {
                    "job_id": 12,
                    "op_id": 5,
                    "machine": 4,
                    "processing_time": 8.191552382450833,
                    "setup_time": 0.7722506991477176,
                    "status": "pending"
                },
                {
                    "job_id": 12,
                    "op_id": 6,
                    "machine": 4,
                    "processing_time": 6.010012673677567,
                    "setup_time": 2.575161919174257,
                    "status": "pending"
                },
                {
                    "job_id": 12,
                    "op_id": 7,
                    "machine": 3,
                    "processing_time": 14.283337172740602,
                    "setup_time": 0.6106590316475945,
                    "status": "pending"
                }
            ],
            "arrival_time": 3,
            "completed_operations": 0,
            "priority": 3,
            "machine_seq": [
                9,
                3,
                9,
                4,
                9,
                4,
                4,
                3
            ],
            "current_operation": 0
        },
        {
            "job_id": 13,
            "operations": [
                {
                    "job_id": 13,
                    "op_id": 0,
                    "machine": 3,
                    "processing_time": 16.153623568123532,
                    "setup_time": 0.0,
                    "status": "pending"
                },
                {
                    "job_id": 13,
                    "op_id": 1,
                    "machine": 5,
                    "processing_time": 17.41100078422876,
                    "setup_time": 1.6435240101343913,
                    "status": "pending"
                },
                {
                    "job_id": 13,
                    "op_id": 2,
                    "machine": 4,
                    "processing_time": 7.550454247723065,
                    "setup_time": 2.1375037773885874,
                    "status": "pending"
                },
                {
                    "job_id": 13,
                    "op_id": 3,
                    "machine": 2,
                    "processing_time": 4.830287869176788,
                    "setup_time": 2.436468837680982,
                    "status": "pending"
                }
            ],
            "arrival_time": 18,
            "completed_operations": 0,
            "priority": 2,
            "machine_seq": [
                3,
                5,
                4,
                2
            ],
            "current_operation": 0
        },
        {
            "job_id": 14,
            "operations": [
                {
                    "job_id": 14,
                    "op_id": 0,
                    "machine": 5,
                    "processing_time": 13.050705614655303,
                    "setup_time": 0.0,
                    "status": "pending"
                },
                {
                    "job_id": 14,
                    "op_id": 1,
                    "machine": 1,
                    "processing_time": 8.777417870579182,
                    "setup_time": 2.5207314550872266,
                    "status": "pending"
                },
                {
                    "job_id": 14,
                    "op_id": 2,
                    "machine": 2,
                    "processing_time": 14.800761445702774,
                    "setup_time": 2.881453549913201,
                    "status": "pending"
                },
                {
                    "job_id": 14,
                    "op_id": 3,
                    "machine": 7,
                    "processing_time": 10.993691657082172,
                    "setup_time": 0.219692862529679,
                    "status": "pending"
                },
                {
                    "job_id": 14,
                    "op_id": 4,
                    "machine": 8,
                    "processing_time": 4.112507961682178,
                    "setup_time": 1.2854526009781586,
                    "status": "pending"
                },
                {
                    "job_id": 14,
                    "op_id": 5,
                    "machine": 7,
                    "processing_time": 14.625063424907923,
                    "setup_time": 0.29515231085844207,
                    "status": "pending"
                }
            ],
            "arrival_time": 35,
            "completed_operations": 0,
            "priority": 5,
            "machine_seq": [
                5,
                1,
                2,
                7,
                8,
                7
            ],
            "current_operation": 0
        },
        {
            "job_id": 15,
            "operations": [
                {
                    "job_id": 15,
                    "op_id": 0,
                    "machine": 0,
                    "processing_time": 16.67442435566291,
                    "setup_time": 0.0,
                    "status": "pending"
                },
                {
                    "job_id": 15,
                    "op_id": 1,
                    "machine": 7,
                    "processing_time": 3.187371258619026,
                    "setup_time": 0.44433098451264963,
                    "status": "pending"
                },
                {
                    "job_id": 15,
                    "op_id": 2,
                    "machine": 6,
                    "processing_time": 4.780021967404163,
                    "setup_time": 0.9620422639280696,
                    "status": "pending"
                },
                {
                    "job_id": 15,
                    "op_id": 3,
                    "machine": 2,
                    "processing_time": 10.373835115958881,
                    "setup_time": 0.2621065758367389,
                    "status": "pending"
                },
                {
                    "job_id": 15,
                    "op_id": 4,
                    "machine": 8,
                    "processing_time": 14.392045972604986,
                    "setup_time": 1.5295880972758629,
                    "status": "pending"
                },
                {
                    "job_id": 15,
                    "op_id": 5,
                    "machine": 7,
                    "processing_time": 5.080545071262961,
                    "setup_time": 2.175949437430744,
                    "status": "pending"
                },
                {
                    "job_id": 15,
                    "op_id": 6,
                    "machine": 1,
                    "processing_time": 2.9732685015574347,
                    "setup_time": 1.7632933833894548,
                    "status": "pending"
                }
            ],
            "arrival_time": 37,
            "completed_operations": 0,
            "priority": 3,
            "machine_seq": [
                0,
                7,
                6,
                2,
                8,
                7,
                1
            ],
            "current_operation": 0
        },
        {
            "job_id": 16,
            "operations": [
                {
                    "job_id": 16,
                    "op_id": 0,
                    "machine": 8,
                    "processing_time": 10.254826617798486,
                    "setup_time": 0.0,
                    "status": "pending"
                },
                {
                    "job_id": 16,
                    "op_id": 1,
                    "machine": 9,
                    "processing_time": 12.589341615795208,
                    "setup_time": 1.6605218008840774,
                    "status": "pending"
                },
                {
                    "job_id": 16,
                    "op_id": 2,
                    "machine": 9,
                    "processing_time": 10.030501430133842,
                    "setup_time": 1.6048393315121445,
                    "status": "pending"
                },
                {
                    "job_id": 16,
                    "op_id": 3,
                    "machine": 0,
                    "processing_time": 6.229996636021947,
                    "setup_time": 1.6843793817744577,
                    "status": "pending"
                },
                {
                    "job_id": 16,
                    "op_id": 4,
                    "machine": 6,
                    "processing_time": 18.005602365628317,
                    "setup_time": 1.1847703763045128,
                    "status": "pending"
                }
            ],
            "arrival_time": 22,
            "completed_operations": 0,
            "priority": 3,
            "machine_seq": [
                8,
                9,
                9,
                0,
                6
            ],
            "current_operation": 0
        },
        {
            "job_id": 17,
            "operations": [
                {
                    "job_id": 17,
                    "op_id": 0,
                    "machine": 3,
                    "processing_time": 12.717404555404785,
                    "setup_time": 0.0,
                    "status": "pending"
                },
                {
                    "job_id": 17,
                    "op_id": 1,
                    "machine": 6,
                    "processing_time": 13.969181558079939,
                    "setup_time": 2.1499687988587595,
                    "status": "pending"
                },
                {
                    "job_id": 17,
                    "op_id": 2,
                    "machine": 8,
                    "processing_time": 11.756364437850488,
                    "setup_time": 2.921349007873467,
                    "status": "pending"
                },
                {
                    "job_id": 17,
                    "op_id": 3,
                    "machine": 3,
                    "processing_time": 4.927688318671031,
                    "setup_time": 1.4273658670132583,
                    "status": "pending"
                }
            ],
            "arrival_time": 3,
            "completed_operations": 0,
            "priority": 5,
            "machine_seq": [
                3,
                6,
                8,
                3
            ],
            "current_operation": 0
        },
        {
            "job_id": 18,
            "operations": [
                {
                    "job_id": 18,
                    "op_id": 0,
                    "machine": 5,
                    "processing_time": 8.831614842358942,
                    "setup_time": 0.0,
                    "status": "pending"
                },
                {
                    "job_id": 18,
                    "op_id": 1,
                    "machine": 1,
                    "processing_time": 8.046083731458467,
                    "setup_time": 1.8966710674619485,
                    "status": "pending"
                },
                {
                    "job_id": 18,
                    "op_id": 2,
                    "machine": 3,
                    "processing_time": 10.041123353217873,
                    "setup_time": 0.3793621103847592,
                    "status": "pending"
                },
                {
                    "job_id": 18,
                    "op_id": 3,
                    "machine": 0,
                    "processing_time": 15.152757426189648,
                    "setup_time": 1.166143198768077,
                    "status": "pending"
                },
                {
                    "job_id": 18,
                    "op_id": 4,
                    "machine": 1,
                    "processing_time": 9.481689308221535,
                    "setup_time": 1.7180704492886727,
                    "status": "pending"
                }
            ],
            "arrival_time": 46,
            "completed_operations": 0,
            "priority": 4,
            "machine_seq": [
                5,
                1,
                3,
                0,
                1
            ],
            "current_operation": 0
        },
        {
            "job_id": 19,
            "operations": [
                {
                    "job_id": 19,
                    "op_id": 0,
                    "machine": 9,
                    "processing_time": 14.05085692211015,
                    "setup_time": 0.0,
                    "status": "pending"
                },
                {
                    "job_id": 19,
                    "op_id": 1,
                    "machine": 6,
                    "processing_time": 5.8773069508585385,
                    "setup_time": 1.2779913844589192,
                    "status": "pending"
                },
                {
                    "job_id": 19,
                    "op_id": 2,
                    "machine": 6,
                    "processing_time": 12.453201371295364,
                    "setup_time": 1.251334964521018,
                    "status": "pending"
                },
                {
                    "job_id": 19,
                    "op_id": 3,
                    "machine": 3,
                    "processing_time": 11.010863868770777,
                    "setup_time": 2.0315262569496784,
                    "status": "pending"
                },
                {
                    "job_id": 19,
                    "op_id": 4,
                    "machine": 0,
                    "processing_time": 12.091467729379962,
                    "setup_time": 2.9802059811114177,
                    "status": "pending"
                },
                {
                    "job_id": 19,
                    "op_id": 5,
                    "machine": 9,
                    "processing_time": 6.59719072702878,
                    "setup_time": 1.9256807413012067,
                    "status": "pending"
                }
            ],
            "arrival_time": 23,
            "completed_operations": 0,
            "priority": 4,
            "machine_seq": [
                9,
                6,
                6,
                3,
                0,
                9
            ],
            "current_operation": 0
        },
        {
            "job_id": 20,
            "operations": [
                {
                    "job_id": 20,
                    "op_id": 0,
                    "machine": 2,
                    "processing_time": 16.950790617368234,
                    "setup_time": 0.0,
                    "status": "pending"
                },
                {
                    "job_id": 20,
                    "op_id": 1,
                    "machine": 6,
                    "processing_time": 2.615360749452701,
                    "setup_time": 2.2872779385161963,
                    "status": "pending"
                },
                {
                    "job_id": 20,
                    "op_id": 2,
                    "machine": 5,
                    "processing_time": 12.484597373140911,
                    "setup_time": 0.8274508296250621,
                    "status": "pending"
                }
            ],
            "arrival_time": 30,
            "completed_operations": 0,
            "priority": 4,
            "machine_seq": [
                2,
                6,
                5
            ],
            "current_operation": 0
        },
        {
            "job_id": 21,
            "operations": [
                {
                    "job_id": 21,
                    "op_id": 0,
                    "machine": 3,
                    "processing_time": 13.142406535542197,
                    "setup_time": 0.0,
                    "status": "pending"
                },
                {
                    "job_id": 21,
                    "op_id": 1,
                    "machine": 2,
                    "processing_time": 13.22081036145854,
                    "setup_time": 0.6459497721832643,
                    "status": "pending"
                },
                {
                    "job_id": 21,
                    "op_id": 2,
                    "machine": 9,
                    "processing_time": 11.526073588164593,
                    "setup_time": 0.14668521542926816,
                    "status": "pending"
                },
                {
                    "job_id": 21,
                    "op_id": 3,
                    "machine": 4,
                    "processing_time": 17.120627969725057,
                    "setup_time": 1.7973852040029816,
                    "status": "pending"
                }
            ],
            "arrival_time": 24,
            "completed_operations": 0,
            "priority": 1,
            "machine_seq": [
                3,
                2,
                9,
                4
            ],
            "current_operation": 0
        },
        {
            "job_id": 22,
            "operations": [
                {
                    "job_id": 22,
                    "op_id": 0,
                    "machine": 0,
                    "processing_time": 14.647532499646829,
                    "setup_time": 0.0,
                    "status": "pending"
                },
                {
                    "job_id": 22,
                    "op_id": 1,
                    "machine": 1,
                    "processing_time": 18.85043498975852,
                    "setup_time": 1.6792378976436102,
                    "status": "pending"
                },
                {
                    "job_id": 22,
                    "op_id": 2,
                    "machine": 9,
                    "processing_time": 16.585878678300034,
                    "setup_time": 1.4287436101837387,
                    "status": "pending"
                },
                {
                    "job_id": 22,
                    "op_id": 3,
                    "machine": 2,
                    "processing_time": 11.242236861910207,
                    "setup_time": 1.9617489146400116,
                    "status": "pending"
                },
                {
                    "job_id": 22,
                    "op_id": 4,
                    "machine": 5,
                    "processing_time": 9.297995407507054,
                    "setup_time": 2.0223061689435067,
                    "status": "pending"
                }
            ],
            "arrival_time": 29,
            "completed_operations": 0,
            "priority": 2,
            "machine_seq": [
                0,
                1,
                9,
                2,
                5
            ],
            "current_operation": 0
        },
        {
            "job_id": 23,
            "operations": [
                {
                    "job_id": 23,
                    "op_id": 0,
                    "machine": 5,
                    "processing_time": 9.14287936920309,
                    "setup_time": 0.0,
                    "status": "pending"
                },
                {
                    "job_id": 23,
                    "op_id": 1,
                    "machine": 0,
                    "processing_time": 13.912644072933766,
                    "setup_time": 2.725427814225941,
                    "status": "pending"
                },
                {
                    "job_id": 23,
                    "op_id": 2,
                    "machine": 8,
                    "processing_time": 2.481241421308619,
                    "setup_time": 0.16156531087477288,
                    "status": "pending"
                }
            ],
            "arrival_time": 13,
            "completed_operations": 0,
            "priority": 2,
            "machine_seq": [
                5,
                0,
                8
            ],
            "current_operation": 0
        },
        {
            "job_id": 24,
            "operations": [
                {
                    "job_id": 24,
                    "op_id": 0,
                    "machine": 2,
                    "processing_time": 3.580535219025534,
                    "setup_time": 0.0,
                    "status": "pending"
                },
                {
                    "job_id": 24,
                    "op_id": 1,
                    "machine": 8,
                    "processing_time": 4.165384689310589,
                    "setup_time": 1.117221833393331,
                    "status": "pending"
                },
                {
                    "job_id": 24,
                    "op_id": 2,
                    "machine": 9,
                    "processing_time": 16.863358858179243,
                    "setup_time": 1.94501204868688,
                    "status": "pending"
                },
                {
                    "job_id": 24,
                    "op_id": 3,
                    "machine": 8,
                    "processing_time": 17.684346264297666,
                    "setup_time": 0.7714396240742057,
                    "status": "pending"
                },
                {
                    "job_id": 24,
                    "op_id": 4,
                    "machine": 5,
                    "processing_time": 5.785527438241184,
                    "setup_time": 0.27350571790480915,
                    "status": "pending"
                },
                {
                    "job_id": 24,
                    "op_id": 5,
                    "machine": 3,
                    "processing_time": 14.743739907993312,
                    "setup_time": 1.169776271831152,
                    "status": "pending"
                }
            ],
            "arrival_time": 49,
            "completed_operations": 0,
            "priority": 2,
            "machine_seq": [
                2,
                8,
                9,
                8,
                5,
                3
            ],
            "current_operation": 0
        },
        {
            "job_id": 25,
            "operations": [
                {
                    "job_id": 25,
                    "op_id": 0,
                    "machine": 4,
                    "processing_time": 8.755171016146086,
                    "setup_time": 0.0,
                    "status": "pending"
                },
                {
                    "job_id": 25,
                    "op_id": 1,
                    "machine": 8,
                    "processing_time": 8.260709765846865,
                    "setup_time": 1.8102702901523398,
                    "status": "pending"
                },
                {
                    "job_id": 25,
                    "op_id": 2,
                    "machine": 1,
                    "processing_time": 14.618222522150354,
                    "setup_time": 0.6859360564889709,
                    "status": "pending"
                }
            ],
            "arrival_time": 14,
            "completed_operations": 0,
            "priority": 2,
            "machine_seq": [
                4,
                8,
                1
            ],
            "current_operation": 0
        },
        {
            "job_id": 26,
            "operations": [
                {
                    "job_id": 26,
                    "op_id": 0,
                    "machine": 2,
                    "processing_time": 8.495450864415616,
                    "setup_time": 0.0,
                    "status": "pending"
                },
                {
                    "job_id": 26,
                    "op_id": 1,
                    "machine": 6,
                    "processing_time": 12.60466582011566,
                    "setup_time": 1.7828206477352193,
                    "status": "pending"
                },
                {
                    "job_id": 26,
                    "op_id": 2,
                    "machine": 0,
                    "processing_time": 10.873917102277938,
                    "setup_time": 2.1953005928310296,
                    "status": "pending"
                },
                {
                    "job_id": 26,
                    "op_id": 3,
                    "machine": 3,
                    "processing_time": 7.128231308030592,
                    "setup_time": 2.0643206119912354,
                    "status": "pending"
                },
                {
                    "job_id": 26,
                    "op_id": 4,
                    "machine": 8,
                    "processing_time": 5.011338158147009,
                    "setup_time": 1.6846191910512576,
                    "status": "pending"
                }
            ],
            "arrival_time": 35,
            "completed_operations": 0,
            "priority": 1,
            "machine_seq": [
                2,
                6,
                0,
                3,
                8
            ],
            "current_operation": 0
        },
        {
            "job_id": 27,
            "operations": [
                {
                    "job_id": 27,
                    "op_id": 0,
                    "machine": 6,
                    "processing_time": 16.507128018203336,
                    "setup_time": 0.0,
                    "status": "pending"
                },
                {
                    "job_id": 27,
                    "op_id": 1,
                    "machine": 3,
                    "processing_time": 10.564392097863958,
                    "setup_time": 0.11107924060266061,
                    "status": "pending"
                },
                {
                    "job_id": 27,
                    "op_id": 2,
                    "machine": 9,
                    "processing_time": 14.624340082998945,
                    "setup_time": 1.244255451916465,
                    "status": "pending"
                }
            ],
            "arrival_time": 17,
            "completed_operations": 0,
            "priority": 5,
            "machine_seq": [
                6,
                3,
                9
            ],
            "current_operation": 0
        },
        {
            "job_id": 28,
            "operations": [
                {
                    "job_id": 28,
                    "op_id": 0,
                    "machine": 0,
                    "processing_time": 8.572891945776322,
                    "setup_time": 0.0,
                    "status": "pending"
                },
                {
                    "job_id": 28,
                    "op_id": 1,
                    "machine": 8,
                    "processing_time": 5.231335106719138,
                    "setup_time": 1.026692726426678,
                    "status": "pending"
                },
                {
                    "job_id": 28,
                    "op_id": 2,
                    "machine": 8,
                    "processing_time": 10.55048232661591,
                    "setup_time": 1.1469987620501478,
                    "status": "pending"
                },
                {
                    "job_id": 28,
                    "op_id": 3,
                    "machine": 8,
                    "processing_time": 19.00877591826829,
                    "setup_time": 1.7301603749474854,
                    "status": "pending"
                },
                {
                    "job_id": 28,
                    "op_id": 4,
                    "machine": 4,
                    "processing_time": 12.674799594043392,
                    "setup_time": 1.3186921617687788,
                    "status": "pending"
                },
                {
                    "job_id": 28,
                    "op_id": 5,
                    "machine": 8,
                    "processing_time": 17.877271377787906,
                    "setup_time": 1.5397456320107534,
                    "status": "pending"
                },
                {
                    "job_id": 28,
                    "op_id": 6,
                    "machine": 2,
                    "processing_time": 9.249904332669185,
                    "setup_time": 1.3895419496865289,
                    "status": "pending"
                },
                {
                    "job_id": 28,
                    "op_id": 7,
                    "machine": 2,
                    "processing_time": 11.456901431200757,
                    "setup_time": 0.8201780874256869,
                    "status": "pending"
                }
            ],
            "arrival_time": 19,
            "completed_operations": 0,
            "priority": 4,
            "machine_seq": [
                0,
                8,
                8,
                8,
                4,
                8,
                2,
                2
            ],
            "current_operation": 0
        },
        {
            "job_id": 29,
            "operations": [
                {
                    "job_id": 29,
                    "op_id": 0,
                    "machine": 9,
                    "processing_time": 12.72915930714186,
                    "setup_time": 0.0,
                    "status": "pending"
                },
                {
                    "job_id": 29,
                    "op_id": 1,
                    "machine": 2,
                    "processing_time": 9.90656035035138,
                    "setup_time": 1.8331928686939691,
                    "status": "pending"
                },
                {
                    "job_id": 29,
                    "op_id": 2,
                    "machine": 3,
                    "processing_time": 9.51422132835437,
                    "setup_time": 2.5974562049412153,
                    "status": "pending"
                },
                {
                    "job_id": 29,
                    "op_id": 3,
                    "machine": 4,
                    "processing_time": 8.321978456624763,
                    "setup_time": 1.8664176915781114,
                    "status": "pending"
                },
                {
                    "job_id": 29,
                    "op_id": 4,
                    "machine": 6,
                    "processing_time": 17.532920145090294,
                    "setup_time": 1.6489183538634449,
                    "status": "pending"
                }
            ],
            "arrival_time": 48,
            "completed_operations": 0,
            "priority": 4,
            "machine_seq": [
                9,
                2,
                3,
                4,
                6
            ],
            "current_operation": 0
        },
        {
            "job_id": 30,
            "operations": [
                {
                    "job_id": 30,
                    "op_id": 0,
                    "machine": 2,
                    "processing_time": 18.919408482717557,
                    "setup_time": 0.0,
                    "status": "pending"
                },
                {
                    "job_id": 30,
                    "op_id": 1,
                    "machine": 0,
                    "processing_time": 8.958448802379788,
                    "setup_time": 2.2400303320343182,
                    "status": "pending"
                },
                {
                    "job_id": 30,
                    "op_id": 2,
                    "machine": 8,
                    "processing_time": 12.12914839218481,
                    "setup_time": 0.2801369003241494,
                    "status": "pending"
                },
                {
                    "job_id": 30,
                    "op_id": 3,
                    "machine": 1,
                    "processing_time": 14.443272614171978,
                    "setup_time": 1.9541892265779828,
                    "status": "pending"
                }
            ],
            "arrival_time": 38,
            "completed_operations": 0,
            "priority": 5,
            "machine_seq": [
                2,
                0,
                8,
                1
            ],
            "current_operation": 0
        },
        {
            "job_id": 31,
            "operations": [
                {
                    "job_id": 31,
                    "op_id": 0,
                    "machine": 2,
                    "processing_time": 13.395499022311004,
                    "setup_time": 0.0,
                    "status": "pending"
                },
                {
                    "job_id": 31,
                    "op_id": 1,
                    "machine": 3,
                    "processing_time": 12.216503340958877,
                    "setup_time": 0.05469019484484117,
                    "status": "pending"
                },
                {
                    "job_id": 31,
                    "op_id": 2,
                    "machine": 7,
                    "processing_time": 12.2981629286089,
                    "setup_time": 0.9323931086060994,
                    "status": "pending"
                },
                {
                    "job_id": 31,
                    "op_id": 3,
                    "machine": 1,
                    "processing_time": 10.311236711644534,
                    "setup_time": 2.2096243843645595,
                    "status": "pending"
                },
                {
                    "job_id": 31,
                    "op_id": 4,
                    "machine": 7,
                    "processing_time": 11.052366911936954,
                    "setup_time": 1.8966987548696825,
                    "status": "pending"
                },
                {
                    "job_id": 31,
                    "op_id": 5,
                    "machine": 8,
                    "processing_time": 5.907221197982426,
                    "setup_time": 0.10494193022727305,
                    "status": "pending"
                },
                {
                    "job_id": 31,
                    "op_id": 6,
                    "machine": 2,
                    "processing_time": 5.290177018530532,
                    "setup_time": 2.295025893118003,
                    "status": "pending"
                }
            ],
            "arrival_time": 3,
            "completed_operations": 0,
            "priority": 2,
            "machine_seq": [
                2,
                3,
                7,
                1,
                7,
                8,
                2
            ],
            "current_operation": 0
        },
        {
            "job_id": 32,
            "operations": [
                {
                    "job_id": 32,
                    "op_id": 0,
                    "machine": 1,
                    "processing_time": 15.457138706355007,
                    "setup_time": 0.0,
                    "status": "pending"
                },
                {
                    "job_id": 32,
                    "op_id": 1,
                    "machine": 3,
                    "processing_time": 2.2644569899868996,
                    "setup_time": 2.6705693617396133,
                    "status": "pending"
                },
                {
                    "job_id": 32,
                    "op_id": 2,
                    "machine": 9,
                    "processing_time": 12.862931469060044,
                    "setup_time": 0.5793727669082548,
                    "status": "pending"
                },
                {
                    "job_id": 32,
                    "op_id": 3,
                    "machine": 3,
                    "processing_time": 10.925147375693282,
                    "setup_time": 1.366910303627284,
                    "status": "pending"
                },
                {
                    "job_id": 32,
                    "op_id": 4,
                    "machine": 6,
                    "processing_time": 11.847909963851196,
                    "setup_time": 1.3555120305250332,
                    "status": "pending"
                }
            ],
            "arrival_time": 33,
            "completed_operations": 0,
            "priority": 1,
            "machine_seq": [
                1,
                3,
                9,
                3,
                6
            ],
            "current_operation": 0
        },
        {
            "job_id": 33,
            "operations": [
                {
                    "job_id": 33,
                    "op_id": 0,
                    "machine": 9,
                    "processing_time": 9.0356783499146,
                    "setup_time": 0.0,
                    "status": "pending"
                },
                {
                    "job_id": 33,
                    "op_id": 1,
                    "machine": 2,
                    "processing_time": 8.106254838745144,
                    "setup_time": 2.5425556252094754,
                    "status": "pending"
                },
                {
                    "job_id": 33,
                    "op_id": 2,
                    "machine": 5,
                    "processing_time": 5.948294879005757,
                    "setup_time": 2.656756056992551,
                    "status": "pending"
                },
                {
                    "job_id": 33,
                    "op_id": 3,
                    "machine": 4,
                    "processing_time": 13.25491539848296,
                    "setup_time": 1.33423589855557,
                    "status": "pending"
                }
            ],
            "arrival_time": 40,
            "completed_operations": 0,
            "priority": 3,
            "machine_seq": [
                9,
                2,
                5,
                4
            ],
            "current_operation": 0
        },
        {
            "job_id": 34,
            "operations": [
                {
                    "job_id": 34,
                    "op_id": 0,
                    "machine": 0,
                    "processing_time": 10.913977771819079,
                    "setup_time": 0.0,
                    "status": "pending"
                },
                {
                    "job_id": 34,
                    "op_id": 1,
                    "machine": 9,
                    "processing_time": 5.140043506014154,
                    "setup_time": 2.9069195995487243,
                    "status": "pending"
                },
                {
                    "job_id": 34,
                    "op_id": 2,
                    "machine": 8,
                    "processing_time": 10.696121481712996,
                    "setup_time": 0.40275430637588083,
                    "status": "pending"
                },
                {
                    "job_id": 34,
                    "op_id": 3,
                    "machine": 1,
                    "processing_time": 3.425428531320607,
                    "setup_time": 2.2880958405709135,
                    "status": "pending"
                }
            ],
            "arrival_time": 25,
            "completed_operations": 0,
            "priority": 4,
            "machine_seq": [
                0,
                9,
                8,
                1
            ],
            "current_operation": 0
        },
        {
            "job_id": 35,
            "operations": [
                {
                    "job_id": 35,
                    "op_id": 0,
                    "machine": 0,
                    "processing_time": 17.025167497826583,
                    "setup_time": 0.0,
                    "status": "pending"
                },
                {
                    "job_id": 35,
                    "op_id": 1,
                    "machine": 2,
                    "processing_time": 7.03662694202138,
                    "setup_time": 0.010162142600036006,
                    "status": "pending"
                },
                {
                    "job_id": 35,
                    "op_id": 2,
                    "machine": 0,
                    "processing_time": 13.13800626314249,
                    "setup_time": 2.4493472048476654,
                    "status": "pending"
                },
                {
                    "job_id": 35,
                    "op_id": 3,
                    "machine": 8,
                    "processing_time": 16.9390198606021,
                    "setup_time": 1.9671883748811756,
                    "status": "pending"
                },
                {
                    "job_id": 35,
                    "op_id": 4,
                    "machine": 8,
                    "processing_time": 10.034556794613229,
                    "setup_time": 1.2120409251798492,
                    "status": "pending"
                },
                {
                    "job_id": 35,
                    "op_id": 5,
                    "machine": 8,
                    "processing_time": 9.343593709903587,
                    "setup_time": 1.1621325735514707,
                    "status": "pending"
                },
                {
                    "job_id": 35,
                    "op_id": 6,
                    "machine": 1,
                    "processing_time": 12.25189688250202,
                    "setup_time": 0.4046021353211553,
                    "status": "pending"
                }
            ],
            "arrival_time": 20,
            "completed_operations": 0,
            "priority": 1,
            "machine_seq": [
                0,
                2,
                0,
                8,
                8,
                8,
                1
            ],
            "current_operation": 0
        },
        {
            "job_id": 36,
            "operations": [
                {
                    "job_id": 36,
                    "op_id": 0,
                    "machine": 9,
                    "processing_time": 13.975419942445539,
                    "setup_time": 0.0,
                    "status": "pending"
                },
                {
                    "job_id": 36,
                    "op_id": 1,
                    "machine": 0,
                    "processing_time": 9.276920670777846,
                    "setup_time": 1.2145867271346746,
                    "status": "pending"
                },
                {
                    "job_id": 36,
                    "op_id": 2,
                    "machine": 4,
                    "processing_time": 14.08939202508571,
                    "setup_time": 0.8019279190448363,
                    "status": "pending"
                }
            ],
            "arrival_time": 5,
            "completed_operations": 0,
            "priority": 2,
            "machine_seq": [
                9,
                0,
                4
            ],
            "current_operation": 0
        },
        {
            "job_id": 37,
            "operations": [
                {
                    "job_id": 37,
                    "op_id": 0,
                    "machine": 0,
                    "processing_time": 7.792953968279603,
                    "setup_time": 0.0,
                    "status": "pending"
                },
                {
                    "job_id": 37,
                    "op_id": 1,
                    "machine": 0,
                    "processing_time": 11.392971514254778,
                    "setup_time": 0.9102358014885025,
                    "status": "pending"
                },
                {
                    "job_id": 37,
                    "op_id": 2,
                    "machine": 5,
                    "processing_time": 12.348277949250221,
                    "setup_time": 1.4114130271429661,
                    "status": "pending"
                },
                {
                    "job_id": 37,
                    "op_id": 3,
                    "machine": 7,
                    "processing_time": 5.940534095096684,
                    "setup_time": 0.45450420832147354,
                    "status": "pending"
                },
                {
                    "job_id": 37,
                    "op_id": 4,
                    "machine": 4,
                    "processing_time": 7.5539206475672716,
                    "setup_time": 2.566431484683278,
                    "status": "pending"
                }
            ],
            "arrival_time": 48,
            "completed_operations": 0,
            "priority": 4,
            "machine_seq": [
                0,
                0,
                5,
                7,
                4
            ],
            "current_operation": 0
        },
        {
            "job_id": 38,
            "operations": [
                {
                    "job_id": 38,
                    "op_id": 0,
                    "machine": 3,
                    "processing_time": 7.895026978148721,
                    "setup_time": 0.0,
                    "status": "pending"
                },
                {
                    "job_id": 38,
                    "op_id": 1,
                    "machine": 5,
                    "processing_time": 9.728221079279393,
                    "setup_time": 2.3125607537158586,
                    "status": "pending"
                },
                {
                    "job_id": 38,
                    "op_id": 2,
                    "machine": 9,
                    "processing_time": 9.733202002260256,
                    "setup_time": 0.7568277898914723,
                    "status": "pending"
                },
                {
                    "job_id": 38,
                    "op_id": 3,
                    "machine": 0,
                    "processing_time": 11.924789948288758,
                    "setup_time": 2.0970773111430367,
                    "status": "pending"
                },
                {
                    "job_id": 38,
                    "op_id": 4,
                    "machine": 0,
                    "processing_time": 11.258453582349906,
                    "setup_time": 0.9726467372018255,
                    "status": "pending"
                },
                {
                    "job_id": 38,
                    "op_id": 5,
                    "machine": 8,
                    "processing_time": 6.316775061870713,
                    "setup_time": 2.060741223237622,
                    "status": "pending"
                },
                {
                    "job_id": 38,
                    "op_id": 6,
                    "machine": 8,
                    "processing_time": 11.16053148551513,
                    "setup_time": 2.792106974096991,
                    "status": "pending"
                },
                {
                    "job_id": 38,
                    "op_id": 7,
                    "machine": 5,
                    "processing_time": 5.86489503267032,
                    "setup_time": 1.3749347480197236,
                    "status": "pending"
                }
            ],
            "arrival_time": 5,
            "completed_operations": 0,
            "priority": 1,
            "machine_seq": [
                3,
                5,
                9,
                0,
                0,
                8,
                8,
                5
            ],
            "current_operation": 0
        },
        {
            "job_id": 39,
            "operations": [
                {
                    "job_id": 39,
                    "op_id": 0,
                    "machine": 1,
                    "processing_time": 17.358587140916466,
                    "setup_time": 0.0,
                    "status": "pending"
                },
                {
                    "job_id": 39,
                    "op_id": 1,
                    "machine": 7,
                    "processing_time": 11.751470293392813,
                    "setup_time": 0.45641900744916397,
                    "status": "pending"
                },
                {
                    "job_id": 39,
                    "op_id": 2,
                    "machine": 7,
                    "processing_time": 11.371313401971253,
                    "setup_time": 0.6825701427389053,
                    "status": "pending"
                }
            ],
            "arrival_time": 16,
            "completed_operations": 0,
            "priority": 4,
            "machine_seq": [
                1,
                7,
                7
            ],
            "current_operation": 0
        },
        {
            "job_id": 40,
            "operations": [
                {
                    "job_id": 40,
                    "op_id": 0,
                    "machine": 0,
                    "processing_time": 13.747523778870196,
                    "setup_time": 0.0,
                    "status": "pending"
                },
                {
                    "job_id": 40,
                    "op_id": 1,
                    "machine": 1,
                    "processing_time": 5.053280579010725,
                    "setup_time": 1.5093760171348165,
                    "status": "pending"
                },
                {
                    "job_id": 40,
                    "op_id": 2,
                    "machine": 0,
                    "processing_time": 14.27433670600304,
                    "setup_time": 0.16046303157205977,
                    "status": "pending"
                }
            ],
            "arrival_time": 19,
            "completed_operations": 0,
            "priority": 4,
            "machine_seq": [
                0,
                1,
                0
            ],
            "current_operation": 0
        },
        {
            "job_id": 41,
            "operations": [
                {
                    "job_id": 41,
                    "op_id": 0,
                    "machine": 1,
                    "processing_time": 8.38212201087935,
                    "setup_time": 0.0,
                    "status": "pending"
                },
                {
                    "job_id": 41,
                    "op_id": 1,
                    "machine": 9,
                    "processing_time": 13.090216283875101,
                    "setup_time": 1.1512535056651376,
                    "status": "pending"
                },
                {
                    "job_id": 41,
                    "op_id": 2,
                    "machine": 2,
                    "processing_time": 10.479944328008942,
                    "setup_time": 1.1906007217526497,
                    "status": "pending"
                }
            ],
            "arrival_time": 20,
            "completed_operations": 0,
            "priority": 3,
            "machine_seq": [
                1,
                9,
                2
            ],
            "current_operation": 0
        },
        {
            "job_id": 42,
            "operations": [
                {
                    "job_id": 42,
                    "op_id": 0,
                    "machine": 8,
                    "processing_time": 11.944420639538503,
                    "setup_time": 0.0,
                    "status": "pending"
                },
                {
                    "job_id": 42,
                    "op_id": 1,
                    "machine": 7,
                    "processing_time": 8.97132481658872,
                    "setup_time": 2.157441880694165,
                    "status": "pending"
                },
                {
                    "job_id": 42,
                    "op_id": 2,
                    "machine": 2,
                    "processing_time": 16.36215935854463,
                    "setup_time": 2.390286584711454,
                    "status": "pending"
                },
                {
                    "job_id": 42,
                    "op_id": 3,
                    "machine": 7,
                    "processing_time": 15.991516039175789,
                    "setup_time": 0.9579339094598748,
                    "status": "pending"
                },
                {
                    "job_id": 42,
                    "op_id": 4,
                    "machine": 7,
                    "processing_time": 8.441154778381357,
                    "setup_time": 1.9708218866226326,
                    "status": "pending"
                },
                {
                    "job_id": 42,
                    "op_id": 5,
                    "machine": 5,
                    "processing_time": 12.577766636243165,
                    "setup_time": 1.234054583394911,
                    "status": "pending"
                },
                {
                    "job_id": 42,
                    "op_id": 6,
                    "machine": 6,
                    "processing_time": 10.179567865250492,
                    "setup_time": 0.5407940547703285,
                    "status": "pending"
                },
                {
                    "job_id": 42,
                    "op_id": 7,
                    "machine": 2,
                    "processing_time": 19.21810000044301,
                    "setup_time": 1.985345764821826,
                    "status": "pending"
                }
            ],
            "arrival_time": 47,
            "completed_operations": 0,
            "priority": 4,
            "machine_seq": [
                8,
                7,
                2,
                7,
                7,
                5,
                6,
                2
            ],
            "current_operation": 0
        },
        {
            "job_id": 43,
            "operations": [
                {
                    "job_id": 43,
                    "op_id": 0,
                    "machine": 1,
                    "processing_time": 4.087140931107147,
                    "setup_time": 0.0,
                    "status": "pending"
                },
                {
                    "job_id": 43,
                    "op_id": 1,
                    "machine": 2,
                    "processing_time": 13.028455948054217,
                    "setup_time": 0.9050434183613145,
                    "status": "pending"
                },
                {
                    "job_id": 43,
                    "op_id": 2,
                    "machine": 5,
                    "processing_time": 9.804556601449132,
                    "setup_time": 0.6056687723418479,
                    "status": "pending"
                },
                {
                    "job_id": 43,
                    "op_id": 3,
                    "machine": 4,
                    "processing_time": 9.198112921243204,
                    "setup_time": 0.0982340549119286,
                    "status": "pending"
                }
            ],
            "arrival_time": 39,
            "completed_operations": 0,
            "priority": 5,
            "machine_seq": [
                1,
                2,
                5,
                4
            ],
            "current_operation": 0
        },
        {
            "job_id": 44,
            "operations": [
                {
                    "job_id": 44,
                    "op_id": 0,
                    "machine": 5,
                    "processing_time": 11.862854412158924,
                    "setup_time": 0.0,
                    "status": "pending"
                },
                {
                    "job_id": 44,
                    "op_id": 1,
                    "machine": 4,
                    "processing_time": 18.44916993104659,
                    "setup_time": 2.664224278268212,
                    "status": "pending"
                },
                {
                    "job_id": 44,
                    "op_id": 2,
                    "machine": 7,
                    "processing_time": 6.9857081929557285,
                    "setup_time": 2.4021317469809045,
                    "status": "pending"
                }
            ],
            "arrival_time": 27,
            "completed_operations": 0,
            "priority": 3,
            "machine_seq": [
                5,
                4,
                7
            ],
            "current_operation": 0
        },
        {
            "job_id": 45,
            "operations": [
                {
                    "job_id": 45,
                    "op_id": 0,
                    "machine": 0,
                    "processing_time": 15.008940299319919,
                    "setup_time": 0.0,
                    "status": "pending"
                },
                {
                    "job_id": 45,
                    "op_id": 1,
                    "machine": 3,
                    "processing_time": 8.534746352378527,
                    "setup_time": 0.8533417215415312,
                    "status": "pending"
                },
                {
                    "job_id": 45,
                    "op_id": 2,
                    "machine": 3,
                    "processing_time": 11.606845556238097,
                    "setup_time": 1.917414721542312,
                    "status": "pending"
                },
                {
                    "job_id": 45,
                    "op_id": 3,
                    "machine": 2,
                    "processing_time": 6.8852619128451575,
                    "setup_time": 0.1522943056971906,
                    "status": "pending"
                }
            ],
            "arrival_time": 29,
            "completed_operations": 0,
            "priority": 3,
            "machine_seq": [
                0,
                3,
                3,
                2
            ],
            "current_operation": 0
        },
        {
            "job_id": 46,
            "operations": [
                {
                    "job_id": 46,
                    "op_id": 0,
                    "machine": 9,
                    "processing_time": 9.686827512274538,
                    "setup_time": 0.0,
                    "status": "pending"
                },
                {
                    "job_id": 46,
                    "op_id": 1,
                    "machine": 1,
                    "processing_time": 17.208473163004083,
                    "setup_time": 1.6102292009043513,
                    "status": "pending"
                },
                {
                    "job_id": 46,
                    "op_id": 2,
                    "machine": 2,
                    "processing_time": 8.940809075874384,
                    "setup_time": 2.881986929369844,
                    "status": "pending"
                }
            ],
            "arrival_time": 21,
            "completed_operations": 0,
            "priority": 1,
            "machine_seq": [
                9,
                1,
                2
            ],
            "current_operation": 0
        },
        {
            "job_id": 47,
            "operations": [
                {
                    "job_id": 47,
                    "op_id": 0,
                    "machine": 7,
                    "processing_time": 7.4902367317683725,
                    "setup_time": 0.0,
                    "status": "pending"
                },
                {
                    "job_id": 47,
                    "op_id": 1,
                    "machine": 5,
                    "processing_time": 15.027115432464692,
                    "setup_time": 0.7133923961610862,
                    "status": "pending"
                },
                {
                    "job_id": 47,
                    "op_id": 2,
                    "machine": 7,
                    "processing_time": 18.098043218193776,
                    "setup_time": 2.6109869265914245,
                    "status": "pending"
                },
                {
                    "job_id": 47,
                    "op_id": 3,
                    "machine": 8,
                    "processing_time": 13.286217077314824,
                    "setup_time": 1.5239311420553718,
                    "status": "pending"
                },
                {
                    "job_id": 47,
                    "op_id": 4,
                    "machine": 0,
                    "processing_time": 12.65424986906292,
                    "setup_time": 2.7276945627317057,
                    "status": "pending"
                },
                {
                    "job_id": 47,
                    "op_id": 5,
                    "machine": 7,
                    "processing_time": 4.50189824078262,
                    "setup_time": 2.653068806675398,
                    "status": "pending"
                },
                {
                    "job_id": 47,
                    "op_id": 6,
                    "machine": 4,
                    "processing_time": 17.789276931744798,
                    "setup_time": 1.0323491269935081,
                    "status": "pending"
                },
                {
                    "job_id": 47,
                    "op_id": 7,
                    "machine": 3,
                    "processing_time": 8.049307033390793,
                    "setup_time": 2.044654832848189,
                    "status": "pending"
                }
            ],
            "arrival_time": 19,
            "completed_operations": 0,
            "priority": 2,
            "machine_seq": [
                7,
                5,
                7,
                8,
                0,
                7,
                4,
                3
            ],
            "current_operation": 0
        },
        {
            "job_id": 48,
            "operations": [
                {
                    "job_id": 48,
                    "op_id": 0,
                    "machine": 6,
                    "processing_time": 9.339811489530614,
                    "setup_time": 0.0,
                    "status": "pending"
                },
                {
                    "job_id": 48,
                    "op_id": 1,
                    "machine": 0,
                    "processing_time": 15.4746228888559,
                    "setup_time": 0.5348860520769325,
                    "status": "pending"
                },
                {
                    "job_id": 48,
                    "op_id": 2,
                    "machine": 7,
                    "processing_time": 17.281477010683048,
                    "setup_time": 2.4272690506322787,
                    "status": "pending"
                },
                {
                    "job_id": 48,
                    "op_id": 3,
                    "machine": 8,
                    "processing_time": 14.969619266896952,
                    "setup_time": 2.0354839146251007,
                    "status": "pending"
                },
                {
                    "job_id": 48,
                    "op_id": 4,
                    "machine": 4,
                    "processing_time": 16.955077276275407,
                    "setup_time": 2.15188709753246,
                    "status": "pending"
                }
            ],
            "arrival_time": 32,
            "completed_operations": 0,
            "priority": 1,
            "machine_seq": [
                6,
                0,
                7,
                8,
                4
            ],
            "current_operation": 0
        },
        {
            "job_id": 49,
            "operations": [
                {
                    "job_id": 49,
                    "op_id": 0,
                    "machine": 7,
                    "processing_time": 14.374752757380627,
                    "setup_time": 0.0,
                    "status": "pending"
                },
                {
                    "job_id": 49,
                    "op_id": 1,
                    "machine": 5,
                    "processing_time": 11.414420277708821,
                    "setup_time": 2.0358546491236997,
                    "status": "pending"
                },
                {
                    "job_id": 49,
                    "op_id": 2,
                    "machine": 0,
                    "processing_time": 14.802438785510923,
                    "setup_time": 2.9813777655255866,
                    "status": "pending"
                },
                {
                    "job_id": 49,
                    "op_id": 3,
                    "machine": 8,
                    "processing_time": 9.417689070433589,
                    "setup_time": 0.6705535381205306,
                    "status": "pending"
                },
                {
                    "job_id": 49,
                    "op_id": 4,
                    "machine": 9,
                    "processing_time": 14.565512890917717,
                    "setup_time": 2.5431053060401125,
                    "status": "pending"
                }
            ],
            "arrival_time": 21,
            "completed_operations": 0,
            "priority": 5,
            "machine_seq": [
                7,
                5,
                0,
                8,
                9
            ],
            "current_operation": 0
        }
    ],
    "machines": [
        {
            "machine_id": 0,
            "status": "available",
            "current_job": null,
            "next_available_time": 0,
            "type": "special"
        },
        {
            "machine_id": 1,
            "status": "available",
            "current_job": null,
            "next_available_time": 0,
            "type": "special"
        },
        {
            "machine_id": 2,
            "status": "available",
            "current_job": null,
            "next_available_time": 0,
            "type": "special"
        },
        {
            "machine_id": 3,
            "status": "available",
            "current_job": null,
            "next_available_time": 0,
            "type": "special"
        },
        {
            "machine_id": 4,
            "status": "available",
            "current_job": null,
            "next_available_time": 0,
            "type": "special"
        },
        {
            "machine_id": 5,
            "status": "available",
            "current_job": null,
            "next_available_time": 0,
            "type": "general"
        },
        {
            "machine_id": 6,
            "status": "available",
            "current_job": null,
            "next_available_time": 0,
            "type": "general"
        },
        {
            "machine_id": 7,
            "status": "available",
            "current_job": null,
            "next_available_time": 0,
            "type": "special"
        },
        {
            "machine_id": 8,
            "status": "available",
            "current_job": null,
            "next_available_time": 0,
            "type": "special"
        },
        {
            "machine_id": 9,
            "status": "available",
            "current_job": null,
            "next_available_time": 0,
            "type": "special"
        }
    ],
    "resources": {
        "resource_capacity": 6,
        "machines": [
            {
                "machine_id": 6,
                "status": "available",
                "current_job": null,
                "next_available_time": 0,
                "type": "general"
            },
            {
                "machine_id": 4,
                "status": "available",
                "current_job": null,
                "next_available_time": 0,
                "type": "special"
            },
            {
                "machine_id": 0,
                "status": "available",
                "current_job": null,
                "next_available_time": 0,
                "type": "special"
            },
            {
                "machine_id": 7,
                "status": "available",
                "current_job": null,
                "next_available_time": 0,
                "type": "special"
            },
            {
                "machine_id": 1,
                "status": "available",
                "current_job": null,
                "next_available_time": 0,
                "type": "special"
            },
            {
                "machine_id": 9,
                "status": "available",
                "current_job": null,
                "next_available_time": 0,
                "type": "special"
            }
        ]
    }
}